{
"meta":{"test_sets":[],"test_metrics":[],"learn_metrics":[{"best_value":"Min","name":"RMSE"}],"launch_mode":"Train","parameters":"","iteration_count":1000,"learn_sets":["learn"],"name":"experiment"},
"iterations":[
{"learn":[2.979154318],"iteration":0,"passed_time":0.0002932578115,"remaining_time":0.2929645536},
{"learn":[2.894796102],"iteration":1,"passed_time":0.0005474729163,"remaining_time":0.2731889852},
{"learn":[2.818963197],"iteration":2,"passed_time":0.0008951488439,"remaining_time":0.2974877991},
{"learn":[2.743995411],"iteration":3,"passed_time":0.001169239478,"remaining_time":0.2911406301},
{"learn":[2.671503512],"iteration":4,"passed_time":0.001448080239,"remaining_time":0.2881679675},
{"learn":[2.605353442],"iteration":5,"passed_time":0.001670544498,"remaining_time":0.2767535385},
{"learn":[2.54035136],"iteration":6,"passed_time":0.001965635692,"remaining_time":0.2788394631},
{"learn":[2.474438085],"iteration":7,"passed_time":0.002196516842,"remaining_time":0.2723680884},
{"learn":[2.415765295],"iteration":8,"passed_time":0.002456148757,"remaining_time":0.2704492687},
{"learn":[2.362818062],"iteration":9,"passed_time":0.002803866353,"remaining_time":0.2775827689},
{"learn":[2.308157488],"iteration":10,"passed_time":0.003128541668,"remaining_time":0.2812843372},
{"learn":[2.254445559],"iteration":11,"passed_time":0.003425382908,"remaining_time":0.2820231928},
{"learn":[2.198688241],"iteration":12,"passed_time":0.003648680523,"remaining_time":0.277019052},
{"learn":[2.151307155],"iteration":13,"passed_time":0.00401098184,"remaining_time":0.282487721},
{"learn":[2.100490003],"iteration":14,"passed_time":0.004234196119,"remaining_time":0.2780455451},
{"learn":[2.051554797],"iteration":15,"passed_time":0.004571080092,"remaining_time":0.2811214257},
{"learn":[2.004770982],"iteration":16,"passed_time":0.004792585993,"remaining_time":0.2771242371},
{"learn":[1.960487547],"iteration":17,"passed_time":0.005066718295,"remaining_time":0.2764176314},
{"learn":[1.924803464],"iteration":18,"passed_time":0.00530030785,"remaining_time":0.2736632632},
{"learn":[1.889363321],"iteration":19,"passed_time":0.005554939633,"remaining_time":0.272192042},
{"learn":[1.853598566],"iteration":20,"passed_time":0.005755486641,"remaining_time":0.2683153058},
{"learn":[1.817242909],"iteration":21,"passed_time":0.006049869483,"remaining_time":0.2689441979},
{"learn":[1.78360302],"iteration":22,"passed_time":0.006256916664,"remaining_time":0.2657829383},
{"learn":[1.7564236],"iteration":23,"passed_time":0.006494756333,"remaining_time":0.2641200909},
{"learn":[1.722067797],"iteration":24,"passed_time":0.006710387077,"remaining_time":0.261705096},
{"learn":[1.687372315],"iteration":25,"passed_time":0.007062063111,"remaining_time":0.2645557489},
{"learn":[1.656327997],"iteration":26,"passed_time":0.007393571941,"remaining_time":0.2664424259},
{"learn":[1.626416443],"iteration":27,"passed_time":0.007672621041,"remaining_time":0.266349559},
{"learn":[1.598375209],"iteration":28,"passed_time":0.007927586166,"remaining_time":0.265437454},
{"learn":[1.572533712],"iteration":29,"passed_time":0.008184218002,"remaining_time":0.2646230487},
{"learn":[1.547060761],"iteration":30,"passed_time":0.008489976146,"remaining_time":0.2653802221},
{"learn":[1.523038482],"iteration":31,"passed_time":0.008777525472,"remaining_time":0.2655201455},
{"learn":[1.499933304],"iteration":32,"passed_time":0.009038782431,"remaining_time":0.2648637155},
{"learn":[1.477434495],"iteration":33,"passed_time":0.009314831451,"remaining_time":0.2646507995},
{"learn":[1.457812284],"iteration":34,"passed_time":0.009537254042,"remaining_time":0.2629557186},
{"learn":[1.437616038],"iteration":35,"passed_time":0.009784093951,"remaining_time":0.2619962936},
{"learn":[1.420618676],"iteration":36,"passed_time":0.01007222663,"remaining_time":0.2621501146},
{"learn":[1.400962093],"iteration":37,"passed_time":0.0104255277,"remaining_time":0.2639304645},
{"learn":[1.382950025],"iteration":38,"passed_time":0.01069424319,"remaining_time":0.2635171208},
{"learn":[1.36497115],"iteration":39,"passed_time":0.01098933439,"remaining_time":0.2637440253},
{"learn":[1.348740919],"iteration":40,"passed_time":0.01132188491,"remaining_time":0.2648216495},
{"learn":[1.335395422],"iteration":41,"passed_time":0.01157635002,"remaining_time":0.2640510315},
{"learn":[1.320955],"iteration":42,"passed_time":0.01184660722,"remaining_time":0.2636558863},
{"learn":[1.307998007],"iteration":43,"passed_time":0.01205357107,"remaining_time":0.261891226},
{"learn":[1.294552503],"iteration":44,"passed_time":0.01238095479,"remaining_time":0.2627513739},
{"learn":[1.282615367],"iteration":45,"passed_time":0.01273646426,"remaining_time":0.2641431935},
{"learn":[1.271742203],"iteration":46,"passed_time":0.01294830324,"remaining_time":0.2625475103},
{"learn":[1.259382655],"iteration":47,"passed_time":0.01317514261,"remaining_time":0.2613069951},
{"learn":[1.248788654],"iteration":48,"passed_time":0.01342560762,"remaining_time":0.2605663845},
{"learn":[1.237240609],"iteration":49,"passed_time":0.01375832481,"remaining_time":0.2614081714},
{"learn":[1.226720407],"iteration":50,"passed_time":0.01409333374,"remaining_time":0.2622465434},
{"learn":[1.216458307],"iteration":51,"passed_time":0.01446480196,"remaining_time":0.2637044666},
{"learn":[1.205270538],"iteration":52,"passed_time":0.01468076605,"remaining_time":0.2623148198},
{"learn":[1.195866283],"iteration":53,"passed_time":0.01488327144,"remaining_time":0.2607328664},
{"learn":[1.186675275],"iteration":54,"passed_time":0.01514940353,"remaining_time":0.2602942971},
{"learn":[1.177866275],"iteration":55,"passed_time":0.01551066315,"remaining_time":0.2614654646},
{"learn":[1.169720726],"iteration":56,"passed_time":0.015817713,"remaining_time":0.2616860238},
{"learn":[1.161382464],"iteration":57,"passed_time":0.01602417683,"remaining_time":0.2602547341},
{"learn":[1.15435106],"iteration":58,"passed_time":0.01635768572,"remaining_time":0.2608912247},
{"learn":[1.14624878],"iteration":59,"passed_time":0.01658210836,"remaining_time":0.2597863643},
{"learn":[1.142213099],"iteration":60,"passed_time":0.01682982329,"remaining_time":0.2590689192},
{"learn":[1.13529627],"iteration":61,"passed_time":0.01713812317,"remaining_time":0.2592832183},
{"learn":[1.128848364],"iteration":62,"passed_time":0.01756067609,"remaining_time":0.2611802143},
{"learn":[1.123345028],"iteration":63,"passed_time":0.01783097496,"remaining_time":0.2607780088},
{"learn":[1.118929066],"iteration":64,"passed_time":0.01814673337,"remaining_time":0.26103378},
{"learn":[1.113548318],"iteration":65,"passed_time":0.01848324234,"remaining_time":0.261565884},
{"learn":[1.107765252],"iteration":66,"passed_time":0.01872695716,"remaining_time":0.2607798661},
{"learn":[1.102324813],"iteration":67,"passed_time":0.01895750497,"remaining_time":0.2598293328},
{"learn":[1.097933068],"iteration":68,"passed_time":0.01934134853,"remaining_time":0.2609680504},
{"learn":[1.092372838],"iteration":69,"passed_time":0.01964039816,"remaining_time":0.2609367184},
{"learn":[1.087944622],"iteration":70,"passed_time":0.01998174058,"remaining_time":0.2614512254},
{"learn":[1.084416],"iteration":71,"passed_time":0.02032466638,"remaining_time":0.2619623667},
{"learn":[1.080128913],"iteration":72,"passed_time":0.02058625669,"remaining_time":0.2614172596},
{"learn":[1.07620415],"iteration":73,"passed_time":0.02081830453,"remaining_time":0.2605101351},
{"learn":[1.071259707],"iteration":74,"passed_time":0.02102068492,"remaining_time":0.2592551141},
{"learn":[1.067650136],"iteration":75,"passed_time":0.02130140074,"remaining_time":0.2589801879},
{"learn":[1.063516841],"iteration":76,"passed_time":0.02156619946,"remaining_time":0.258514313},
{"learn":[1.059807003],"iteration":77,"passed_time":0.02183862338,"remaining_time":0.2581437276},
{"learn":[1.055354808],"iteration":78,"passed_time":0.02215059002,"remaining_time":0.2582366254},
{"learn":[1.052704962],"iteration":79,"passed_time":0.02239184645,"remaining_time":0.2575062342},
{"learn":[1.048803586],"iteration":80,"passed_time":0.02265068668,"remaining_time":0.2569874204},
{"learn":[1.045600707],"iteration":81,"passed_time":0.02287777606,"remaining_time":0.2561194929},
{"learn":[1.042396715],"iteration":82,"passed_time":0.02313436623,"remaining_time":0.2555929377},
{"learn":[1.039526637],"iteration":83,"passed_time":0.02335712216,"remaining_time":0.2547038559},
{"learn":[1.037211834],"iteration":84,"passed_time":0.02355916921,"remaining_time":0.2536075274},
{"learn":[1.03439743],"iteration":85,"passed_time":0.0237717582,"remaining_time":0.2526440349},
{"learn":[1.032005714],"iteration":86,"passed_time":0.02401834811,"remaining_time":0.2520546186},
{"learn":[1.029206768],"iteration":87,"passed_time":0.02421939513,"remaining_time":0.2510010041},
{"learn":[1.026822031],"iteration":88,"passed_time":0.02441860877,"remaining_time":0.2499477819},
{"learn":[1.0245644],"iteration":89,"passed_time":0.02465719846,"remaining_time":0.2493116733},
{"learn":[1.022757914],"iteration":90,"passed_time":0.02490232999,"remaining_time":0.2487496479},
{"learn":[1.020503913],"iteration":91,"passed_time":0.02521437996,"remaining_time":0.2488549675},
{"learn":[1.019864516],"iteration":92,"passed_time":0.02533438316,"remaining_time":0.247078339},
{"learn":[1.018442829],"iteration":93,"passed_time":0.0255373469,"remaining_time":0.2461365563},
{"learn":[1.016971103],"iteration":94,"passed_time":0.02591052351,"remaining_time":0.2468318292},
{"learn":[1.014585049],"iteration":95,"passed_time":0.02617803063,"remaining_time":0.2465097885},
{"learn":[1.012076822],"iteration":96,"passed_time":0.02640166159,"remaining_time":0.2457804167},
{"learn":[1.010913797],"iteration":97,"passed_time":0.02673625384,"remaining_time":0.2460826629},
{"learn":[1.009557101],"iteration":98,"passed_time":0.02694180098,"remaining_time":0.2451976028},
{"learn":[1.007711803],"iteration":99,"passed_time":0.02720743305,"remaining_time":0.2448668975},
{"learn":[1.005157641],"iteration":100,"passed_time":0.02749635742,"remaining_time":0.2447448051},
{"learn":[1.00244994],"iteration":101,"passed_time":0.02775494764,"remaining_time":0.2443523821},
{"learn":[1.000673577],"iteration":102,"passed_time":0.0280364968,"remaining_time":0.2441625013},
{"learn":[0.9986112451],"iteration":103,"passed_time":0.02830342058,"remaining_time":0.2438448542},
{"learn":[0.9968224962],"iteration":104,"passed_time":0.02860809536,"remaining_time":0.2438499557},
{"learn":[0.9951827873],"iteration":105,"passed_time":0.02887589416,"remaining_time":0.2435382017},
{"learn":[0.9931242395],"iteration":106,"passed_time":0.02928657177,"remaining_time":0.2444197064},
{"learn":[0.9910816267],"iteration":107,"passed_time":0.02952199471,"remaining_time":0.2438298081},
{"learn":[0.988759537],"iteration":108,"passed_time":0.02976108441,"remaining_time":0.2432763872},
{"learn":[0.9873467404],"iteration":109,"passed_time":0.03002546645,"remaining_time":0.2429333195},
{"learn":[0.9854255817],"iteration":110,"passed_time":0.03026484783,"remaining_time":0.2423914389},
{"learn":[0.9849778522],"iteration":111,"passed_time":0.03054727202,"remaining_time":0.2421962281},
{"learn":[0.9836110326],"iteration":112,"passed_time":0.03081748755,"remaining_time":0.2419036412},
{"learn":[0.9819619412],"iteration":113,"passed_time":0.03105761894,"remaining_time":0.2413776349},
{"learn":[0.9805836981],"iteration":114,"passed_time":0.03129958372,"remaining_time":0.2408707095},
{"learn":[0.978984451],"iteration":115,"passed_time":0.03154021513,"remaining_time":0.2403581912},
{"learn":[0.9778038353],"iteration":116,"passed_time":0.03187972417,"remaining_time":0.2405965508},
{"learn":[0.9769625454],"iteration":117,"passed_time":0.03223131687,"remaining_time":0.2409154363},
{"learn":[0.974974779],"iteration":118,"passed_time":0.03248074018,"remaining_time":0.2404666563},
{"learn":[0.9739631338],"iteration":119,"passed_time":0.03268995409,"remaining_time":0.23972633},
{"learn":[0.9730531561],"iteration":120,"passed_time":0.03289662626,"remaining_time":0.2389763181},
{"learn":[0.9721587641],"iteration":121,"passed_time":0.03312567403,"remaining_time":0.2383962442},
{"learn":[0.9704845604],"iteration":122,"passed_time":0.03336651378,"remaining_time":0.237905956},
{"learn":[0.9687764672],"iteration":123,"passed_time":0.03364981299,"remaining_time":0.2377196466},
{"learn":[0.9681309044],"iteration":124,"passed_time":0.03390911156,"remaining_time":0.237363781},
{"learn":[0.9670311394],"iteration":125,"passed_time":0.03425257905,"remaining_time":0.2375932864},
{"learn":[0.9659861287],"iteration":126,"passed_time":0.03448271018,"remaining_time":0.2370346928},
{"learn":[0.9650320473],"iteration":127,"passed_time":0.03469234076,"remaining_time":0.2363415714},
{"learn":[0.9644773313],"iteration":128,"passed_time":0.03493105545,"remaining_time":0.2358523201},
{"learn":[0.9637718462],"iteration":129,"passed_time":0.03530527375,"remaining_time":0.2362737551},
{"learn":[0.963153903],"iteration":130,"passed_time":0.03560507341,"remaining_time":0.2361893801},
{"learn":[0.9626159132],"iteration":131,"passed_time":0.03588987266,"remaining_time":0.236003102},
{"learn":[0.9619260887],"iteration":132,"passed_time":0.03611608702,"remaining_time":0.2354334394},
{"learn":[0.9606169623],"iteration":133,"passed_time":0.03633130108,"remaining_time":0.2347978115},
{"learn":[0.9593240215],"iteration":134,"passed_time":0.03666397661,"remaining_time":0.2349210353},
{"learn":[0.9583729814],"iteration":135,"passed_time":0.03699969389,"remaining_time":0.2350568788},
{"learn":[0.9574516035],"iteration":136,"passed_time":0.03727070111,"remaining_time":0.2347782121},
{"learn":[0.9567491755],"iteration":137,"passed_time":0.0374695814,"remaining_time":0.2340491244},
{"learn":[0.9560222885],"iteration":138,"passed_time":0.03771679632,"remaining_time":0.2336270621},
{"learn":[0.9552045731],"iteration":139,"passed_time":0.03800563735,"remaining_time":0.2334632009},
{"learn":[0.9545497006],"iteration":140,"passed_time":0.03849856715,"remaining_time":0.2345409162},
{"learn":[0.9538917506],"iteration":141,"passed_time":0.03869598907,"remaining_time":0.2338109762},
{"learn":[0.9537619209],"iteration":142,"passed_time":0.03878740817,"remaining_time":0.2324532084},
{"learn":[0.9522181897],"iteration":143,"passed_time":0.03904924848,"remaining_time":0.2321260882},
{"learn":[0.9517008929],"iteration":144,"passed_time":0.03922971162,"remaining_time":0.2313200237},
{"learn":[0.9508195853],"iteration":145,"passed_time":0.03963418073,"remaining_time":0.2318328106},
{"learn":[0.9505885012],"iteration":146,"passed_time":0.03984393632,"remaining_time":0.2312032495},
{"learn":[0.9496192569],"iteration":147,"passed_time":0.04005827536,"remaining_time":0.2306057473},
{"learn":[0.949071608],"iteration":148,"passed_time":0.0403187823,"remaining_time":0.2302770721},
{"learn":[0.9483412276],"iteration":149,"passed_time":0.04060358155,"remaining_time":0.2300869621},
{"learn":[0.9475779109],"iteration":150,"passed_time":0.04083671276,"remaining_time":0.2296050936},
{"learn":[0.9468382187],"iteration":151,"passed_time":0.04113192896,"remaining_time":0.2294728668},
{"learn":[0.9458471007],"iteration":152,"passed_time":0.04138789411,"remaining_time":0.2291212177},
{"learn":[0.9453610552],"iteration":153,"passed_time":0.04164473428,"remaining_time":0.2287756182},
{"learn":[0.9441825892],"iteration":154,"passed_time":0.04186786523,"remaining_time":0.2282473943},
{"learn":[0.9432462602],"iteration":155,"passed_time":0.04207895418,"remaining_time":0.2276579316},
{"learn":[0.9425563536],"iteration":156,"passed_time":0.04234775301,"remaining_time":0.2273831579},
{"learn":[0.941364551],"iteration":157,"passed_time":0.04255950865,"remaining_time":0.2268044702},
{"learn":[0.9404434948],"iteration":158,"passed_time":0.04276997259,"remaining_time":0.2262235657},
{"learn":[0.9402149339],"iteration":159,"passed_time":0.04295589421,"remaining_time":0.2255184446},
{"learn":[0.9398698048],"iteration":160,"passed_time":0.04327190263,"remaining_time":0.2254976789},
{"learn":[0.939445971],"iteration":161,"passed_time":0.04357320232,"remaining_time":0.2253971824},
{"learn":[0.93923883],"iteration":162,"passed_time":0.04394467055,"remaining_time":0.2256545353},
{"learn":[0.9386263712],"iteration":163,"passed_time":0.044211886,"remaining_time":0.2253727847},
{"learn":[0.9380702047],"iteration":164,"passed_time":0.04447201793,"remaining_time":0.2250553634},
{"learn":[0.9376478762],"iteration":165,"passed_time":0.04468481526,"remaining_time":0.2245008188},
{"learn":[0.9368638405],"iteration":166,"passed_time":0.04498982339,"remaining_time":0.2244103167},
{"learn":[0.9361642033],"iteration":167,"passed_time":0.04526395569,"remaining_time":0.224164352},
{"learn":[0.9352785424],"iteration":168,"passed_time":0.04549942029,"remaining_time":0.2237279187},
{"learn":[0.9346734447],"iteration":169,"passed_time":0.04581251197,"remaining_time":0.2236728525},
{"learn":[0.9342649156],"iteration":170,"passed_time":0.04615102098,"remaining_time":0.2237379906},
{"learn":[0.9338049952],"iteration":171,"passed_time":0.04638898566,"remaining_time":0.2233144193},
{"learn":[0.9336546452],"iteration":172,"passed_time":0.04651715574,"remaining_time":0.2223681375},
{"learn":[0.9326539858],"iteration":173,"passed_time":0.04679328809,"remaining_time":0.222133655},
{"learn":[0.9321892944],"iteration":174,"passed_time":0.04706412864,"remaining_time":0.2218737493},
{"learn":[0.9313684947],"iteration":175,"passed_time":0.04732630229,"remaining_time":0.2215731425},
{"learn":[0.9308627929],"iteration":176,"passed_time":0.04764976924,"remaining_time":0.2215579666},
{"learn":[0.9306487246],"iteration":177,"passed_time":0.04790194262,"remaining_time":0.2212100946},
{"learn":[0.9303180673],"iteration":178,"passed_time":0.04816957475,"remaining_time":0.2209341948},
{"learn":[0.9291021227],"iteration":179,"passed_time":0.04838074704,"remaining_time":0.220401181},
{"learn":[0.9283456058],"iteration":180,"passed_time":0.04868346344,"remaining_time":0.2202859478},
{"learn":[0.9280934946],"iteration":181,"passed_time":0.0489373452,"remaining_time":0.2199491669},
{"learn":[0.9275320947],"iteration":182,"passed_time":0.04928627116,"remaining_time":0.220037615},
{"learn":[0.9273624608],"iteration":183,"passed_time":0.04953577781,"remaining_time":0.2196804059},
{"learn":[0.926039717],"iteration":184,"passed_time":0.04983170236,"remaining_time":0.2195288509},
{"learn":[0.9259540001],"iteration":185,"passed_time":0.04994795546,"remaining_time":0.2185894395},
{"learn":[0.9256938125],"iteration":186,"passed_time":0.05025104686,"remaining_time":0.2184711289},
{"learn":[0.9251721959],"iteration":187,"passed_time":0.05051247049,"remaining_time":0.2181708832},
{"learn":[0.9248030339],"iteration":188,"passed_time":0.05077235241,"remaining_time":0.2178644328},
{"learn":[0.924069706],"iteration":189,"passed_time":0.05097127438,"remaining_time":0.2172985908},
{"learn":[0.9235811653],"iteration":190,"passed_time":0.05126444886,"remaining_time":0.2171358069},
{"learn":[0.9228061541],"iteration":191,"passed_time":0.05163091695,"remaining_time":0.2172801088},
{"learn":[0.9227254519],"iteration":192,"passed_time":0.05177429577,"remaining_time":0.2164863041},
{"learn":[0.9221883395],"iteration":193,"passed_time":0.05203471937,"remaining_time":0.2161854836},
{"learn":[0.9217412639],"iteration":194,"passed_time":0.05222684949,"remaining_time":0.2156031479},
{"learn":[0.920790811],"iteration":195,"passed_time":0.05247452276,"remaining_time":0.2152526342},
{"learn":[0.9199098379],"iteration":196,"passed_time":0.05277644746,"remaining_time":0.2151243011},
{"learn":[0.9196795669],"iteration":197,"passed_time":0.05308420566,"remaining_time":0.2150178431},
{"learn":[0.9194291025],"iteration":198,"passed_time":0.05328596104,"remaining_time":0.2144826874},
{"learn":[0.9193527621],"iteration":199,"passed_time":0.05348821642,"remaining_time":0.2139528657},
{"learn":[0.9187841487],"iteration":200,"passed_time":0.05375222346,"remaining_time":0.2136717738},
{"learn":[0.9186366945],"iteration":201,"passed_time":0.05404102282,"remaining_time":0.2134887931},
{"learn":[0.9185239043],"iteration":202,"passed_time":0.05444199183,"remaining_time":0.21374516},
{"learn":[0.9181769528],"iteration":203,"passed_time":0.05463499697,"remaining_time":0.2131836156},
{"learn":[0.9169855998],"iteration":204,"passed_time":0.05492683808,"remaining_time":0.2130089574},
{"learn":[0.9161084125],"iteration":205,"passed_time":0.05516684447,"remaining_time":0.2126333714},
{"learn":[0.9157079416],"iteration":206,"passed_time":0.05541176766,"remaining_time":0.2122779312},
{"learn":[0.9148167358],"iteration":207,"passed_time":0.05573531795,"remaining_time":0.2122229414},
{"learn":[0.9142823269],"iteration":208,"passed_time":0.05596461572,"remaining_time":0.2118086652},
{"learn":[0.9136664116],"iteration":209,"passed_time":0.05619483019,"remaining_time":0.2113995993},
{"learn":[0.9135201816],"iteration":210,"passed_time":0.05646450404,"remaining_time":0.2111397805},
{"learn":[0.9134272368],"iteration":211,"passed_time":0.05673001111,"remaining_time":0.2108643809},
{"learn":[0.9131283099],"iteration":212,"passed_time":0.05708318718,"remaining_time":0.2109129968},
{"learn":[0.9129703285],"iteration":213,"passed_time":0.05736148626,"remaining_time":0.2106828421},
{"learn":[0.9128926759],"iteration":214,"passed_time":0.05758757562,"remaining_time":0.2102616133},
{"learn":[0.9127601028],"iteration":215,"passed_time":0.05783741561,"remaining_time":0.2099283974},
{"learn":[0.9119311776],"iteration":216,"passed_time":0.05810388104,"remaining_time":0.2096559394},
{"learn":[0.9113606776],"iteration":217,"passed_time":0.05835576275,"remaining_time":0.2093312223},
{"learn":[0.9111612634],"iteration":218,"passed_time":0.05865172896,"remaining_time":0.209164385},
{"learn":[0.9108579059],"iteration":219,"passed_time":0.05885690109,"remaining_time":0.2086744675},
{"learn":[0.9100550352],"iteration":220,"passed_time":0.05908682389,"remaining_time":0.2082743702},
{"learn":[0.9099260155],"iteration":221,"passed_time":0.05933603886,"remaining_time":0.2079434155},
{"learn":[0.9098201663],"iteration":222,"passed_time":0.05960967115,"remaining_time":0.2076982712},
{"learn":[0.9090805474],"iteration":223,"passed_time":0.05994772182,"remaining_time":0.2076760363},
{"learn":[0.9087462799],"iteration":224,"passed_time":0.06016526928,"remaining_time":0.2072359275},
{"learn":[0.9086199904],"iteration":225,"passed_time":0.06042790127,"remaining_time":0.2069521929},
{"learn":[0.9083451789],"iteration":226,"passed_time":0.06067257446,"remaining_time":0.2066074892},
{"learn":[0.9081122515],"iteration":227,"passed_time":0.06092658122,"remaining_time":0.2062952663},
{"learn":[0.9070619156],"iteration":228,"passed_time":0.06121417222,"remaining_time":0.2060966235},
{"learn":[0.9067583478],"iteration":229,"passed_time":0.06148822118,"remaining_time":0.2058518709},
{"learn":[0.9064659034],"iteration":230,"passed_time":0.06174006123,"remaining_time":0.2055329311},
{"learn":[0.9063559029],"iteration":231,"passed_time":0.06206369485,"remaining_time":0.2054522312},
{"learn":[0.9052395199],"iteration":232,"passed_time":0.06246433052,"remaining_time":0.2056229249},
{"learn":[0.9051086053],"iteration":233,"passed_time":0.06285850768,"remaining_time":0.2057675935},
{"learn":[0.9050073326],"iteration":234,"passed_time":0.0631856414,"remaining_time":0.2056894284},
{"learn":[0.9049121812],"iteration":235,"passed_time":0.06338297999,"remaining_time":0.2051889691},
{"learn":[0.9043772486],"iteration":236,"passed_time":0.06372090566,"remaining_time":0.2051436752},
{"learn":[0.9040758155],"iteration":237,"passed_time":0.06405387286,"remaining_time":0.2050800467},
{"learn":[0.9038431473],"iteration":238,"passed_time":0.0643496724,"remaining_time":0.2048958188},
{"learn":[0.9037519381],"iteration":239,"passed_time":0.06469284821,"remaining_time":0.204860686},
{"learn":[0.9034010689],"iteration":240,"passed_time":0.06498039754,"remaining_time":0.204647808},
{"learn":[0.9032974389],"iteration":241,"passed_time":0.06528336394,"remaining_time":0.2044826028},
{"learn":[0.90315084],"iteration":242,"passed_time":0.06552253698,"remaining_time":0.2041175329},
{"learn":[0.9030650989],"iteration":243,"passed_time":0.06578808572,"remaining_time":0.2038352164},
{"learn":[0.9028290951],"iteration":244,"passed_time":0.06604313418,"remaining_time":0.2035206788},
{"learn":[0.9021524975],"iteration":245,"passed_time":0.06645602018,"remaining_time":0.2036904033},
{"learn":[0.9016002629],"iteration":246,"passed_time":0.06672356897,"remaining_time":0.2034123378},
{"learn":[0.9013736731],"iteration":247,"passed_time":0.06705516114,"remaining_time":0.2033285531},
{"learn":[0.9012942343],"iteration":248,"passed_time":0.06735133569,"remaining_time":0.2031359562},
{"learn":[0.9012119817],"iteration":249,"passed_time":0.06768051113,"remaining_time":0.2030415334},
{"learn":[0.9010746202],"iteration":250,"passed_time":0.06791855914,"remaining_time":0.2026733099},
{"learn":[0.9010002481],"iteration":251,"passed_time":0.06823444255,"remaining_time":0.2025371549},
{"learn":[0.9009163965],"iteration":252,"passed_time":0.06850132466,"remaining_time":0.2022548993},
{"learn":[0.8991953083],"iteration":253,"passed_time":0.06879199907,"remaining_time":0.2020426429},
{"learn":[0.8984172023],"iteration":254,"passed_time":0.0691047574,"remaining_time":0.2018942912},
{"learn":[0.8983464833],"iteration":255,"passed_time":0.06936576435,"remaining_time":0.2015942526},
{"learn":[0.8975252057],"iteration":256,"passed_time":0.06958385349,"remaining_time":0.2011704403},
{"learn":[0.8966759602],"iteration":257,"passed_time":0.06982569327,"remaining_time":0.2008165287},
{"learn":[0.8963496522],"iteration":258,"passed_time":0.07004190736,"remaining_time":0.2003901674},
{"learn":[0.8953895956],"iteration":259,"passed_time":0.07030066425,"remaining_time":0.200086506},
{"learn":[0.8953222503],"iteration":260,"passed_time":0.07060025557,"remaining_time":0.1998988079},
{"learn":[0.8949139403],"iteration":261,"passed_time":0.07082838664,"remaining_time":0.199508967},
{"learn":[0.8948486855],"iteration":262,"passed_time":0.07102226681,"remaining_time":0.199024375},
{"learn":[0.8938975045],"iteration":263,"passed_time":0.0712446894,"remaining_time":0.1986215583},
{"learn":[0.8926140734],"iteration":264,"passed_time":0.07149302935,"remaining_time":0.1982919871},
{"learn":[0.8920310176],"iteration":265,"passed_time":0.07172045207,"remaining_time":0.1979053076},
{"learn":[0.8912550016],"iteration":266,"passed_time":0.07191716565,"remaining_time":0.1974355147},
{"learn":[0.8903278727],"iteration":267,"passed_time":0.07212992131,"remaining_time":0.1970115761},
{"learn":[0.8893968395],"iteration":268,"passed_time":0.07238288638,"remaining_time":0.1966984756},
{"learn":[0.8887099578],"iteration":269,"passed_time":0.07266910234,"remaining_time":0.1964757211},
{"learn":[0.8880960144],"iteration":270,"passed_time":0.07302998695,"remaining_time":0.1964533597},
{"learn":[0.8871028938],"iteration":271,"passed_time":0.07336603757,"remaining_time":0.1963620417},
{"learn":[0.8861921139],"iteration":272,"passed_time":0.07364454499,"remaining_time":0.1961156931},
{"learn":[0.8859052624],"iteration":273,"passed_time":0.07393042761,"remaining_time":0.1958886512},
{"learn":[0.8852495413],"iteration":274,"passed_time":0.0741918929,"remaining_time":0.1955968086},
{"learn":[0.8837882111],"iteration":275,"passed_time":0.07445635828,"remaining_time":0.1953130558},
{"learn":[0.883360314],"iteration":276,"passed_time":0.07481020104,"remaining_time":0.1952627269},
{"learn":[0.8819048375],"iteration":277,"passed_time":0.07502404007,"remaining_time":0.1948466077},
{"learn":[0.88114526],"iteration":278,"passed_time":0.07531308944,"remaining_time":0.1946262992},
{"learn":[0.8800398471],"iteration":279,"passed_time":0.07558618004,"remaining_time":0.194364463},
{"learn":[0.8799362795],"iteration":280,"passed_time":0.07592889751,"remaining_time":0.1942807022},
{"learn":[0.8797597716],"iteration":281,"passed_time":0.07624823934,"remaining_time":0.1941355881},
{"learn":[0.879614486],"iteration":282,"passed_time":0.07659379022,"remaining_time":0.1940556452},
{"learn":[0.8787912042],"iteration":283,"passed_time":0.07691288205,"remaining_time":0.1939071252},
{"learn":[0.8787451843],"iteration":284,"passed_time":0.0771963896,"remaining_time":0.1936681353},
{"learn":[0.8784000345],"iteration":285,"passed_time":0.07740502016,"remaining_time":0.1932419035},
{"learn":[0.878267057],"iteration":286,"passed_time":0.07774648759,"remaining_time":0.1931471974},
{"learn":[0.8774712259],"iteration":287,"passed_time":0.078074663,"remaining_time":0.1930179168},
{"learn":[0.8771819144],"iteration":288,"passed_time":0.07839054641,"remaining_time":0.192857019},
{"learn":[0.8764634521],"iteration":289,"passed_time":0.0787332222,"remaining_time":0.1927606475},
{"learn":[0.8761009583],"iteration":290,"passed_time":0.07895772818,"remaining_time":0.1923746711},
{"learn":[0.8751665453],"iteration":291,"passed_time":0.07917077553,"remaining_time":0.1919620174},
{"learn":[0.8746316904],"iteration":292,"passed_time":0.079501326,"remaining_time":0.1918342576},
{"learn":[0.8745059829],"iteration":293,"passed_time":0.07978312517,"remaining_time":0.1915880489},
{"learn":[0.8734301626],"iteration":294,"passed_time":0.07998188046,"remaining_time":0.1911431381},
{"learn":[0.8731542115],"iteration":295,"passed_time":0.08026197126,"remaining_time":0.190893337},
{"learn":[0.8728456056],"iteration":296,"passed_time":0.08063202278,"remaining_time":0.1908562694},
{"learn":[0.872454208],"iteration":297,"passed_time":0.08087640429,"remaining_time":0.1905209255},
{"learn":[0.8713131785],"iteration":298,"passed_time":0.08109341007,"remaining_time":0.1901220082},
{"learn":[0.8711577802],"iteration":299,"passed_time":0.08140012657,"remaining_time":0.1899336287},
{"learn":[0.8708824014],"iteration":300,"passed_time":0.08172842699,"remaining_time":0.1897945863},
{"learn":[0.8701472362],"iteration":301,"passed_time":0.08199460074,"remaining_time":0.1895106997},
{"learn":[0.8699935969],"iteration":302,"passed_time":0.08231015082,"remaining_time":0.1893405119},
{"learn":[0.8694696899],"iteration":303,"passed_time":0.08255644904,"remaining_time":0.1890108175},
{"learn":[0.8693227306],"iteration":304,"passed_time":0.08279224699,"remaining_time":0.1886577431},
{"learn":[0.8686516496],"iteration":305,"passed_time":0.08307354615,"remaining_time":0.1884086308},
{"learn":[0.8680139587],"iteration":306,"passed_time":0.08334563673,"remaining_time":0.188138522},
{"learn":[0.8675522568],"iteration":307,"passed_time":0.08358630981,"remaining_time":0.1877978129},
{"learn":[0.8668344894],"iteration":308,"passed_time":0.08379744043,"remaining_time":0.1873916872},
{"learn":[0.8665992806],"iteration":309,"passed_time":0.0840801563,"remaining_time":0.1871461543},
{"learn":[0.8656110833],"iteration":310,"passed_time":0.0843156209,"remaining_time":0.1867957003},
{"learn":[0.8647582586],"iteration":311,"passed_time":0.08457554449,"remaining_time":0.1864999186},
{"learn":[0.86415779],"iteration":312,"passed_time":0.08504484866,"remaining_time":0.186663933},
{"learn":[0.8630814906],"iteration":313,"passed_time":0.08529068854,"remaining_time":0.1863357081},
{"learn":[0.8621262019],"iteration":314,"passed_time":0.08560682196,"remaining_time":0.1861608668},
{"learn":[0.8610928938],"iteration":315,"passed_time":0.08584149488,"remaining_time":0.1858088054},
{"learn":[0.8610568166],"iteration":316,"passed_time":0.08608658474,"remaining_time":0.1854799286},
{"learn":[0.8601125492],"iteration":317,"passed_time":0.08638867612,"remaining_time":0.1852738274},
{"learn":[0.859583964],"iteration":318,"passed_time":0.08667730881,"remaining_time":0.1850383928},
{"learn":[0.8586460741],"iteration":319,"passed_time":0.0870296932,"remaining_time":0.184938098},
{"learn":[0.8579959932],"iteration":320,"passed_time":0.08728715839,"remaining_time":0.1846354534},
{"learn":[0.8570921201],"iteration":321,"passed_time":0.08758987478,"remaining_time":0.1844283699},
{"learn":[0.856827046],"iteration":322,"passed_time":0.08786946556,"remaining_time":0.1841722235},
{"learn":[0.8563461372],"iteration":323,"passed_time":0.08817147361,"remaining_time":0.1839627042},
{"learn":[0.8563120916],"iteration":324,"passed_time":0.08843131386,"remaining_time":0.1836650365},
{"learn":[0.8560879304],"iteration":325,"passed_time":0.08878369825,"remaining_time":0.1835589344},
{"learn":[0.8554325568],"iteration":326,"passed_time":0.08900528749,"remaining_time":0.183182136},
{"learn":[0.8547907763],"iteration":327,"passed_time":0.08925029401,"remaining_time":0.1828542609},
{"learn":[0.8543133604],"iteration":328,"passed_time":0.08950900924,"remaining_time":0.1825548486},
{"learn":[0.8541851252],"iteration":329,"passed_time":0.08970130603,"remaining_time":0.1821208334},
{"learn":[0.8528733533],"iteration":330,"passed_time":0.08994422916,"remaining_time":0.1817906021},
{"learn":[0.8527442051],"iteration":331,"passed_time":0.09016781845,"remaining_time":0.1814219962},
{"learn":[0.8523291967],"iteration":332,"passed_time":0.09041053325,"remaining_time":0.1810925696},
{"learn":[0.8520849403],"iteration":333,"passed_time":0.09062928908,"remaining_time":0.1807158878},
{"learn":[0.8514152755],"iteration":334,"passed_time":0.09091429667,"remaining_time":0.1804716635},
{"learn":[0.8511692073],"iteration":335,"passed_time":0.09121488801,"remaining_time":0.180257993},
{"learn":[0.850447073],"iteration":336,"passed_time":0.091464853,"remaining_time":0.1799442063},
{"learn":[0.8497934124],"iteration":337,"passed_time":0.09181636236,"remaining_time":0.1798296801},
{"learn":[0.8492235565],"iteration":338,"passed_time":0.09214562113,"remaining_time":0.1796703704},
{"learn":[0.848906845],"iteration":339,"passed_time":0.09245996284,"remaining_time":0.1794811043},
{"learn":[0.8485163535],"iteration":340,"passed_time":0.09274997057,"remaining_time":0.179244078},
{"learn":[0.8479267005],"iteration":341,"passed_time":0.09303956161,"remaining_time":0.1790059402},
{"learn":[0.8474256024],"iteration":342,"passed_time":0.09327110945,"remaining_time":0.1786563233},
{"learn":[0.8472145037],"iteration":343,"passed_time":0.09357128411,"remaining_time":0.1784382627},
{"learn":[0.8466728809],"iteration":344,"passed_time":0.09384624977,"remaining_time":0.1781718655},
{"learn":[0.8458643389],"iteration":345,"passed_time":0.09426367755,"remaining_time":0.1781746969},
{"learn":[0.8445737537],"iteration":346,"passed_time":0.0944745165,"remaining_time":0.177786338},
{"learn":[0.8444592868],"iteration":347,"passed_time":0.0947335234,"remaining_time":0.177489245},
{"learn":[0.8440914458],"iteration":348,"passed_time":0.09498353006,"remaining_time":0.1771755819},
{"learn":[0.8439287019],"iteration":349,"passed_time":0.09526299584,"remaining_time":0.1769169923},
{"learn":[0.8438189792],"iteration":350,"passed_time":0.09623510507,"remaining_time":0.1779389834},
{"learn":[0.8431593598],"iteration":351,"passed_time":0.0964803616,"remaining_time":0.1776115748},
{"learn":[0.8425601921],"iteration":352,"passed_time":0.09674603534,"remaining_time":0.1773220534},
{"learn":[0.8420923324],"iteration":353,"passed_time":0.09701445916,"remaining_time":0.1770376854},
{"learn":[0.8417123915],"iteration":354,"passed_time":0.09739117753,"remaining_time":0.1769501676},
{"learn":[0.8410024471],"iteration":355,"passed_time":0.09769168553,"remaining_time":0.1767231615},
{"learn":[0.8408130374],"iteration":356,"passed_time":0.09794619231,"remaining_time":0.1764128898},
{"learn":[0.8401457115],"iteration":357,"passed_time":0.09816844823,"remaining_time":0.1760450943},
{"learn":[0.8395078782],"iteration":358,"passed_time":0.09841224639,"remaining_time":0.1757165736},
{"learn":[0.8390679116],"iteration":359,"passed_time":0.09866329474,"remaining_time":0.1754014129},
{"learn":[0.838970941],"iteration":360,"passed_time":0.09885479985,"remaining_time":0.1749812108},
{"learn":[0.8387592108],"iteration":361,"passed_time":0.09904767998,"remaining_time":0.1745646957},
{"learn":[0.8383132606],"iteration":362,"passed_time":0.09935335479,"remaining_time":0.1743473471},
{"learn":[0.8376386727],"iteration":363,"passed_time":0.09957552738,"remaining_time":0.1739836138},
{"learn":[0.837117896],"iteration":364,"passed_time":0.0998015334,"remaining_time":0.1736273252},
{"learn":[0.8370883707],"iteration":365,"passed_time":0.1000307895,"remaining_time":0.1732773785},
{"learn":[0.8365977218],"iteration":366,"passed_time":0.1003168805,"remaining_time":0.1730261181},
{"learn":[0.8359555467],"iteration":367,"passed_time":0.100563887,"remaining_time":0.1727075451},
{"learn":[0.8356011857],"iteration":368,"passed_time":0.1008511447,"remaining_time":0.1724581905},
{"learn":[0.8347745132],"iteration":369,"passed_time":0.1011245686,"remaining_time":0.1721850763},
{"learn":[0.834023134],"iteration":370,"passed_time":0.1013443662,"remaining_time":0.1718210413},
{"learn":[0.8331701088],"iteration":371,"passed_time":0.1016478326,"remaining_time":0.1715990292},
{"learn":[0.8323739118],"iteration":372,"passed_time":0.1018846306,"remaining_time":0.171264513},
{"learn":[0.8323251934],"iteration":373,"passed_time":0.1021072615,"remaining_time":0.1709068066},
{"learn":[0.8322889498],"iteration":374,"passed_time":0.1023108086,"remaining_time":0.1705180143},
{"learn":[0.8318305354],"iteration":375,"passed_time":0.1025789824,"remaining_time":0.1702374601},
{"learn":[0.8312168766],"iteration":376,"passed_time":0.1028942824,"remaining_time":0.1700348487},
{"learn":[0.8310383067],"iteration":377,"passed_time":0.1032307497,"remaining_time":0.1698664718},
{"learn":[0.8303500148],"iteration":378,"passed_time":0.10361526,"remaining_time":0.1697759273},
{"learn":[0.8299400874],"iteration":379,"passed_time":0.103865725,"remaining_time":0.1694651302},
{"learn":[0.8295054992],"iteration":380,"passed_time":0.1041434407,"remaining_time":0.1691989234},
{"learn":[0.8293165965],"iteration":381,"passed_time":0.1044085311,"remaining_time":0.168912231},
{"learn":[0.8286619323],"iteration":382,"passed_time":0.1046849551,"remaining_time":0.1686439095},
{"learn":[0.828637476],"iteration":383,"passed_time":0.1049533373,"remaining_time":0.1683626452},
{"learn":[0.8284641416],"iteration":384,"passed_time":0.1052603455,"remaining_time":0.1681431493},
{"learn":[0.8281515342],"iteration":385,"passed_time":0.1055366445,"remaining_time":0.1678743516},
{"learn":[0.8273263914],"iteration":386,"passed_time":0.1058135685,"remaining_time":0.1676065052},
{"learn":[0.8272798592],"iteration":387,"passed_time":0.1060060737,"remaining_time":0.1672054564},
{"learn":[0.8271487073],"iteration":388,"passed_time":0.1062117458,"remaining_time":0.1668261612},
{"learn":[0.8265549413],"iteration":389,"passed_time":0.106468461,"remaining_time":0.1665275928},
{"learn":[0.8258488936],"iteration":390,"passed_time":0.1067182593,"remaining_time":0.1662184653},
{"learn":[0.8250472177],"iteration":391,"passed_time":0.1069670993,"remaining_time":0.165908154},
{"learn":[0.8248730579],"iteration":392,"passed_time":0.1071651462,"remaining_time":0.1655197042},
{"learn":[0.8242921592],"iteration":393,"passed_time":0.107395569,"remaining_time":0.1651820173},
{"learn":[0.8237266387],"iteration":394,"passed_time":0.1075924076,"remaining_time":0.1647934344},
{"learn":[0.8231044968],"iteration":395,"passed_time":0.1078424142,"remaining_time":0.1644869147},
{"learn":[0.8230785503],"iteration":396,"passed_time":0.1081272552,"remaining_time":0.1642335891},
{"learn":[0.8226268771],"iteration":397,"passed_time":0.1083269688,"remaining_time":0.1638513448},
{"learn":[0.8223401025],"iteration":398,"passed_time":0.1086283518,"remaining_time":0.1636231565},
{"learn":[0.8216152152],"iteration":399,"passed_time":0.1089944033,"remaining_time":0.1634916049},
{"learn":[0.8207380349],"iteration":400,"passed_time":0.1093197453,"remaining_time":0.1632980734},
{"learn":[0.8201145993],"iteration":401,"passed_time":0.1095930442,"remaining_time":0.1630264688},
{"learn":[0.8200360488],"iteration":402,"passed_time":0.1098690516,"remaining_time":0.1627588679},
{"learn":[0.8194228427],"iteration":403,"passed_time":0.1101456006,"remaining_time":0.1624920246},
{"learn":[0.8192573432],"iteration":404,"passed_time":0.1104261914,"remaining_time":0.1622310713},
{"learn":[0.818827669],"iteration":405,"passed_time":0.1107434915,"remaining_time":0.162023729},
{"learn":[0.8177259543],"iteration":406,"passed_time":0.1110407078,"remaining_time":0.1617865841},
{"learn":[0.8170251484],"iteration":407,"passed_time":0.1113055065,"remaining_time":0.1615021075},
{"learn":[0.8160955906],"iteration":408,"passed_time":0.1116409321,"remaining_time":0.1613197821},
{"learn":[0.8155463825],"iteration":409,"passed_time":0.1118481459,"remaining_time":0.16095221},
{"learn":[0.8151363271],"iteration":410,"passed_time":0.1121653211,"remaining_time":0.1607430027},
{"learn":[0.8146215564],"iteration":411,"passed_time":0.112412536,"remaining_time":0.1604334251},
{"learn":[0.81445506],"iteration":412,"passed_time":0.1127930461,"remaining_time":0.1603136031},
{"learn":[0.8139612925],"iteration":413,"passed_time":0.1129994683,"remaining_time":0.1599461073},
{"learn":[0.8137056086],"iteration":414,"passed_time":0.1132507666,"remaining_time":0.159642647},
{"learn":[0.8132078074],"iteration":415,"passed_time":0.1134968565,"remaining_time":0.1593321255},
{"learn":[0.8130416881],"iteration":416,"passed_time":0.1137674054,"remaining_time":0.1590561088},
{"learn":[0.8121494221],"iteration":417,"passed_time":0.1140014116,"remaining_time":0.1587292382},
{"learn":[0.8114136311],"iteration":418,"passed_time":0.1142128756,"remaining_time":0.158371553},
{"learn":[0.8112785945],"iteration":419,"passed_time":0.1144212978,"remaining_time":0.1580103637},
{"learn":[0.811237376],"iteration":420,"passed_time":0.1146823881,"remaining_time":0.1577223342},
{"learn":[0.8107514303],"iteration":421,"passed_time":0.1149275613,"remaining_time":0.1574126314},
{"learn":[0.8101666869],"iteration":422,"passed_time":0.1151829014,"remaining_time":0.157117102},
{"learn":[0.8099146982],"iteration":423,"passed_time":0.115454492,"remaining_time":0.1568438382},
{"learn":[0.8097556881],"iteration":424,"passed_time":0.1156992069,"remaining_time":0.156534221},
{"learn":[0.8090632844],"iteration":425,"passed_time":0.115915921,"remaining_time":0.1561871799},
{"learn":[0.8084840718],"iteration":426,"passed_time":0.1161595525,"remaining_time":0.1558768702},
{"learn":[0.8081267527],"iteration":427,"passed_time":0.1163840584,"remaining_time":0.1555413117},
{"learn":[0.8073514584],"iteration":428,"passed_time":0.1165836888,"remaining_time":0.1551731615},
{"learn":[0.8066173819],"iteration":429,"passed_time":0.1169234478,"remaining_time":0.1549915471},
{"learn":[0.8062234608],"iteration":430,"passed_time":0.1171369118,"remaining_time":0.154642466},
{"learn":[0.8058809639],"iteration":431,"passed_time":0.1173295003,"remaining_time":0.1542665652},
{"learn":[0.8055933598],"iteration":432,"passed_time":0.1175234221,"remaining_time":0.1538932571},
{"learn":[0.8052751848],"iteration":433,"passed_time":0.1177503032,"remaining_time":0.1535637594},
{"learn":[0.8045819145],"iteration":434,"passed_time":0.117969059,"remaining_time":0.1532241801},
{"learn":[0.8039724132],"iteration":435,"passed_time":0.1182151072,"remaining_time":0.1529204598},
{"learn":[0.8035084227],"iteration":436,"passed_time":0.1184308213,"remaining_time":0.1525779231},
{"learn":[0.8031450535],"iteration":437,"passed_time":0.118794956,"remaining_time":0.1524264047},
{"learn":[0.8031253369],"iteration":438,"passed_time":0.1190804219,"remaining_time":0.1521733866},
{"learn":[0.8019054761],"iteration":439,"passed_time":0.1193286369,"remaining_time":0.1518728106},
{"learn":[0.8013818815],"iteration":440,"passed_time":0.1195856437,"remaining_time":0.1515836164},
{"learn":[0.8012163848],"iteration":441,"passed_time":0.1198282335,"remaining_time":0.1512763672},
{"learn":[0.8007184427],"iteration":442,"passed_time":0.1200419475,"remaining_time":0.1509331033},
{"learn":[0.800266906],"iteration":443,"passed_time":0.1203320803,"remaining_time":0.1506861185},
{"learn":[0.7999984359],"iteration":444,"passed_time":0.1206057959,"remaining_time":0.1504184645},
{"learn":[0.799471729],"iteration":445,"passed_time":0.1208909285,"remaining_time":0.150164965},
{"learn":[0.7991457964],"iteration":446,"passed_time":0.1217835356,"remaining_time":0.1506628528},
{"learn":[0.7987024072],"iteration":447,"passed_time":0.1220079166,"remaining_time":0.1503311829},
{"learn":[0.7984138849],"iteration":448,"passed_time":0.1224496367,"remaining_time":0.1502667034},
{"learn":[0.7979571354],"iteration":449,"passed_time":0.1226871847,"remaining_time":0.1499510035},
{"learn":[0.7975053653],"iteration":450,"passed_time":0.1228922735,"remaining_time":0.1495961378},
{"learn":[0.797240205],"iteration":451,"passed_time":0.1231609473,"remaining_time":0.1493190246},
{"learn":[0.7966222268],"iteration":452,"passed_time":0.1234446632,"remaining_time":0.149060112},
{"learn":[0.7958719828],"iteration":453,"passed_time":0.1236912531,"remaining_time":0.1487564409},
{"learn":[0.7952423228],"iteration":454,"passed_time":0.1238966335,"remaining_time":0.14840366},
{"learn":[0.79448705],"iteration":455,"passed_time":0.1241301398,"remaining_time":0.148085079},
{"learn":[0.7937480366],"iteration":456,"passed_time":0.1243437288,"remaining_time":0.1477432051},
{"learn":[0.7930353856],"iteration":457,"passed_time":0.1246477786,"remaining_time":0.1475089432},
{"learn":[0.7923690852],"iteration":458,"passed_time":0.1249367446,"remaining_time":0.1472565987},
{"learn":[0.7920937733],"iteration":459,"passed_time":0.1251945848,"remaining_time":0.1469675561},
{"learn":[0.7917842521],"iteration":460,"passed_time":0.1254424247,"remaining_time":0.1466669565},
{"learn":[0.7913708805],"iteration":461,"passed_time":0.1258576858,"remaining_time":0.1465615475},
{"learn":[0.7907451125],"iteration":462,"passed_time":0.1260896086,"remaining_time":0.1462421595},
{"learn":[0.7906137147],"iteration":463,"passed_time":0.1263548657,"remaining_time":0.1459616552},
{"learn":[0.7901732781],"iteration":464,"passed_time":0.1265869135,"remaining_time":0.1456430081},
{"learn":[0.7899096672],"iteration":465,"passed_time":0.1268589625,"remaining_time":0.1453705707},
{"learn":[0.7893666593],"iteration":466,"passed_time":0.1270999689,"remaining_time":0.1450627054},
{"learn":[0.7888309237],"iteration":467,"passed_time":0.1273009742,"remaining_time":0.1447096545},
{"learn":[0.7884486909],"iteration":468,"passed_time":0.1275241468,"remaining_time":0.1443823496},
{"learn":[0.7880073928],"iteration":469,"passed_time":0.1279423246,"remaining_time":0.1442753874},
{"learn":[0.7875047248],"iteration":470,"passed_time":0.1281658306,"remaining_time":0.1439484594},
{"learn":[0.7870423054],"iteration":471,"passed_time":0.1283734611,"remaining_time":0.1436042108},
{"learn":[0.786897655],"iteration":472,"passed_time":0.1287017615,"remaining_time":0.1433949859},
{"learn":[0.7858127369],"iteration":473,"passed_time":0.1290557293,"remaining_time":0.1432137418},
{"learn":[0.7857968374],"iteration":474,"passed_time":0.1292869021,"remaining_time":0.1428960497},
{"learn":[0.7853169328],"iteration":475,"passed_time":0.1296059523,"remaining_time":0.1426754601},
{"learn":[0.7847696384],"iteration":476,"passed_time":0.1299234191,"remaining_time":0.1424527216},
{"learn":[0.7844568083],"iteration":477,"passed_time":0.1302303856,"remaining_time":0.1422181198},
{"learn":[0.7840576368],"iteration":478,"passed_time":0.130508143,"remaining_time":0.1419514457},
{"learn":[0.7837998365],"iteration":479,"passed_time":0.1307048149,"remaining_time":0.1415968828},
{"learn":[0.7833478474],"iteration":480,"passed_time":0.1309675719,"remaining_time":0.1413142824},
{"learn":[0.7831933179],"iteration":481,"passed_time":0.1312622464,"remaining_time":0.1410660656},
{"learn":[0.78267622],"iteration":482,"passed_time":0.1316622154,"remaining_time":0.1409303631},
{"learn":[0.7823899306],"iteration":483,"passed_time":0.1319643484,"remaining_time":0.140689264},
{"learn":[0.7816195858],"iteration":484,"passed_time":0.1322337723,"remaining_time":0.1404131809},
{"learn":[0.7815348321],"iteration":485,"passed_time":0.1325012377,"remaining_time":0.1401350539},
{"learn":[0.7809017851],"iteration":486,"passed_time":0.1327407441,"remaining_time":0.139827519},
{"learn":[0.7805505117],"iteration":487,"passed_time":0.1330343769,"remaining_time":0.1395770512},
{"learn":[0.7797427165],"iteration":488,"passed_time":0.1333316349,"remaining_time":0.1393301951},
{"learn":[0.779062361],"iteration":489,"passed_time":0.1336132257,"remaining_time":0.1390668267},
{"learn":[0.7787157752],"iteration":490,"passed_time":0.133885983,"remaining_time":0.1387942267},
{"learn":[0.7785922003],"iteration":491,"passed_time":0.1341211142,"remaining_time":0.1384827765},
{"learn":[0.7784085433],"iteration":492,"passed_time":0.134349287,"remaining_time":0.1381644797},
{"learn":[0.7778214008],"iteration":493,"passed_time":0.1345693345,"remaining_time":0.1378382252},
{"learn":[0.7769592999],"iteration":494,"passed_time":0.1347685481,"remaining_time":0.1374911451},
{"learn":[0.776572972],"iteration":495,"passed_time":0.1350338885,"remaining_time":0.1372118545},
{"learn":[0.7763478905],"iteration":496,"passed_time":0.135288187,"remaining_time":0.1369214448},
{"learn":[0.7762064313],"iteration":497,"passed_time":0.1355098596,"remaining_time":0.1365982922},
{"learn":[0.7758436452],"iteration":498,"passed_time":0.135826243,"remaining_time":0.1363706367},
{"learn":[0.775481153],"iteration":499,"passed_time":0.1360876249,"remaining_time":0.1360876249},
{"learn":[0.7748709628],"iteration":500,"passed_time":0.136301589,"remaining_time":0.1357574709},
{"learn":[0.7747633607],"iteration":501,"passed_time":0.1365863466,"remaining_time":0.1354980091},
{"learn":[0.774451192],"iteration":502,"passed_time":0.1368185611,"remaining_time":0.1351865305},
{"learn":[0.7741822608],"iteration":503,"passed_time":0.1370776513,"remaining_time":0.1349018156},
{"learn":[0.7736924462],"iteration":504,"passed_time":0.1372953654,"remaining_time":0.1345766453},
{"learn":[0.7732335187],"iteration":505,"passed_time":0.1376066654,"remaining_time":0.1343432662},
{"learn":[0.7728824647],"iteration":506,"passed_time":0.1379144653,"remaining_time":0.1341061763},
{"learn":[0.772664258],"iteration":507,"passed_time":0.1382180567,"remaining_time":0.1338647321},
{"learn":[0.7723831599],"iteration":508,"passed_time":0.1385012309,"remaining_time":0.1336033485},
{"learn":[0.771827864],"iteration":509,"passed_time":0.1387454457,"remaining_time":0.1333044479},
{"learn":[0.7713093368],"iteration":510,"passed_time":0.1389703684,"remaining_time":0.1329872997},
{"learn":[0.7710128562],"iteration":511,"passed_time":0.139205083,"remaining_time":0.1326798447},
{"learn":[0.7706422681],"iteration":512,"passed_time":0.1394185887,"remaining_time":0.1323525393},
{"learn":[0.7700572033],"iteration":513,"passed_time":0.1396433447,"remaining_time":0.1320363142},
{"learn":[0.7695632428],"iteration":514,"passed_time":0.1399527279,"remaining_time":0.1318001418},
{"learn":[0.7694370402],"iteration":515,"passed_time":0.1401614835,"remaining_time":0.1314692984},
{"learn":[0.7690839871],"iteration":516,"passed_time":0.1403954064,"remaining_time":0.1311624396},
{"learn":[0.7686090487],"iteration":517,"passed_time":0.1407072897,"remaining_time":0.1309284047},
{"learn":[0.7683555144],"iteration":518,"passed_time":0.1410491321,"remaining_time":0.1307218353},
{"learn":[0.7678407458],"iteration":519,"passed_time":0.1413623488,"remaining_time":0.1304883219},
{"learn":[0.7672453905],"iteration":520,"passed_time":0.1416231891,"remaining_time":0.1302063485},
{"learn":[0.7665674474],"iteration":521,"passed_time":0.1419147385,"remaining_time":0.1299525766},
{"learn":[0.7664294037],"iteration":522,"passed_time":0.1421718287,"remaining_time":0.1296672319},
{"learn":[0.7656701159],"iteration":523,"passed_time":0.1425416302,"remaining_time":0.1294843816},
{"learn":[0.7653367741],"iteration":524,"passed_time":0.1429526411,"remaining_time":0.1293381039},
{"learn":[0.7650955],"iteration":525,"passed_time":0.1433251094,"remaining_time":0.1291560872},
{"learn":[0.7648123893],"iteration":526,"passed_time":0.1436029918,"remaining_time":0.1288884537},
{"learn":[0.7646568726],"iteration":527,"passed_time":0.1439672932,"remaining_time":0.1286980348},
{"learn":[0.7643172042],"iteration":528,"passed_time":0.1442264251,"remaining_time":0.1284133199},
{"learn":[0.7640832794],"iteration":529,"passed_time":0.1445253497,"remaining_time":0.1281639894},
{"learn":[0.7638903754],"iteration":530,"passed_time":0.1448537334,"remaining_time":0.1279404915},
{"learn":[0.7637280657],"iteration":531,"passed_time":0.1450836979,"remaining_time":0.12763002},
{"learn":[0.763673182],"iteration":532,"passed_time":0.1452746197,"remaining_time":0.1272856424},
{"learn":[0.763450997],"iteration":533,"passed_time":0.1455245846,"remaining_time":0.1269933641},
{"learn":[0.7628944191],"iteration":534,"passed_time":0.1459100116,"remaining_time":0.126818982},
{"learn":[0.7625643905],"iteration":535,"passed_time":0.1462612293,"remaining_time":0.1266141985},
{"learn":[0.7624499895],"iteration":536,"passed_time":0.1465431534,"remaining_time":0.1263491249},
{"learn":[0.7622366641],"iteration":537,"passed_time":0.1467865766,"remaining_time":0.1260509264},
{"learn":[0.7621358587],"iteration":538,"passed_time":0.1470749176,"remaining_time":0.1257913488},
{"learn":[0.7618336835],"iteration":539,"passed_time":0.1473367163,"remaining_time":0.1255090546},
{"learn":[0.7614179799],"iteration":540,"passed_time":0.1475579721,"remaining_time":0.1251924385},
{"learn":[0.7612003833],"iteration":541,"passed_time":0.147827771,"remaining_time":0.1249171939},
{"learn":[0.7608802841],"iteration":542,"passed_time":0.148064319,"remaining_time":0.1246139848},
{"learn":[0.7607655063],"iteration":543,"passed_time":0.1483884109,"remaining_time":0.1243844033},
{"learn":[0.7597266051],"iteration":544,"passed_time":0.1486223755,"remaining_time":0.1240792309},
{"learn":[0.7593476169],"iteration":545,"passed_time":0.1488295477,"remaining_time":0.1237520415},
{"learn":[0.758659653],"iteration":546,"passed_time":0.1491734735,"remaining_time":0.1235385439},
{"learn":[0.7579618242],"iteration":547,"passed_time":0.1494047713,"remaining_time":0.1232316727},
{"learn":[0.7577020533],"iteration":548,"passed_time":0.1496892372,"remaining_time":0.1229687541},
{"learn":[0.7575155397],"iteration":549,"passed_time":0.1499795783,"remaining_time":0.1227105641},
{"learn":[0.7572966312],"iteration":550,"passed_time":0.1502997535,"remaining_time":0.1224765686},
{"learn":[0.7569793815],"iteration":551,"passed_time":0.1505528853,"remaining_time":0.1221878489},
{"learn":[0.7565099161],"iteration":552,"passed_time":0.1508383512,"remaining_time":0.1219253942},
{"learn":[0.7558397734],"iteration":553,"passed_time":0.1511180253,"remaining_time":0.1216581937},
{"learn":[0.7551215607],"iteration":554,"passed_time":0.1513726571,"remaining_time":0.1213708692},
{"learn":[0.7549434221],"iteration":555,"passed_time":0.1515736624,"remaining_time":0.1210408384},
{"learn":[0.7546215588],"iteration":556,"passed_time":0.1519085047,"remaining_time":0.1208177156},
{"learn":[0.7540185579],"iteration":557,"passed_time":0.1521693866,"remaining_time":0.1205356073},
{"learn":[0.7535729053],"iteration":558,"passed_time":0.1524183516,"remaining_time":0.1202441736},
{"learn":[0.7529960142],"iteration":559,"passed_time":0.152656983,"remaining_time":0.1199447723},
{"learn":[0.7527975329],"iteration":560,"passed_time":0.1528951976,"remaining_time":0.1196452616},
{"learn":[0.7524103337],"iteration":561,"passed_time":0.1531131618,"remaining_time":0.1193301866},
{"learn":[0.7520951415],"iteration":562,"passed_time":0.1533591267,"remaining_time":0.1190371907},
{"learn":[0.7514068682],"iteration":563,"passed_time":0.153673135,"remaining_time":0.1187969625},
{"learn":[0.7511187793],"iteration":564,"passed_time":0.1539324336,"remaining_time":0.1185143515},
{"learn":[0.7505776215],"iteration":565,"passed_time":0.1541654815,"remaining_time":0.1182116943},
{"learn":[0.7503292428],"iteration":566,"passed_time":0.1543702786,"remaining_time":0.1178877084},
{"learn":[0.7496859363],"iteration":567,"passed_time":0.1545822009,"remaining_time":0.1175695613},
{"learn":[0.7493122552],"iteration":568,"passed_time":0.1547921648,"remaining_time":0.1172503041},
{"learn":[0.7491496771],"iteration":569,"passed_time":0.1550089623,"remaining_time":0.1169365856},
{"learn":[0.7489264469],"iteration":570,"passed_time":0.1552293432,"remaining_time":0.1166258988},
{"learn":[0.7484785888],"iteration":571,"passed_time":0.1554595576,"remaining_time":0.1163228858},
{"learn":[0.7478125463],"iteration":572,"passed_time":0.1557404401,"remaining_time":0.1160578847},
{"learn":[0.7477569505],"iteration":573,"passed_time":0.1559843216,"remaining_time":0.1157653676},
{"learn":[0.7477136619],"iteration":574,"passed_time":0.1562334116,"remaining_time":0.1154768694},
{"learn":[0.7474782841],"iteration":575,"passed_time":0.1565671705,"remaining_time":0.1152508338},
{"learn":[0.746929555],"iteration":576,"passed_time":0.1568003017,"remaining_time":0.1149506544},
{"learn":[0.7465942986],"iteration":577,"passed_time":0.1571968122,"remaining_time":0.1147699909},
{"learn":[0.7460033039],"iteration":578,"passed_time":0.1575290711,"remaining_time":0.1145418634},
{"learn":[0.7458242347],"iteration":579,"passed_time":0.1578075368,"remaining_time":0.1142744232},
{"learn":[0.7455148036],"iteration":580,"passed_time":0.1580486266,"remaining_time":0.1139799906},
{"learn":[0.7450682634],"iteration":581,"passed_time":0.1583662184,"remaining_time":0.113740686},
{"learn":[0.7445721229],"iteration":582,"passed_time":0.158639434,"remaining_time":0.1134693722},
{"learn":[0.7443891862],"iteration":583,"passed_time":0.1589022743,"remaining_time":0.1131906612},
{"learn":[0.744224715],"iteration":584,"passed_time":0.1592042407,"remaining_time":0.1129397605},
{"learn":[0.7437939643],"iteration":585,"passed_time":0.1596297937,"remaining_time":0.1127759976},
{"learn":[0.7435630933],"iteration":586,"passed_time":0.159854258,"remaining_time":0.1124698613},
{"learn":[0.7431446086],"iteration":587,"passed_time":0.1601235569,"remaining_time":0.1121954174},
{"learn":[0.7426716826],"iteration":588,"passed_time":0.1604078978,"remaining_time":0.1119314872},
{"learn":[0.7419532252],"iteration":589,"passed_time":0.1607134892,"remaining_time":0.1116822552},
{"learn":[0.7414920674],"iteration":590,"passed_time":0.1610314977,"remaining_time":0.1114414257},
{"learn":[0.7408092633],"iteration":591,"passed_time":0.1613542563,"remaining_time":0.1112036091},
{"learn":[0.7406276576],"iteration":592,"passed_time":0.1616300136,"remaining_time":0.1109332471},
{"learn":[0.7403252182],"iteration":593,"passed_time":0.1618283523,"remaining_time":0.1106099512},
{"learn":[0.7399694795],"iteration":594,"passed_time":0.1620902342,"remaining_time":0.1103303275},
{"learn":[0.7396168088],"iteration":595,"passed_time":0.1623666583,"remaining_time":0.1100606207},
{"learn":[0.7392129206],"iteration":596,"passed_time":0.162643874,"remaining_time":0.1097914258},
{"learn":[0.7385337426],"iteration":597,"passed_time":0.1629604658,"remaining_time":0.1095486743},
{"learn":[0.7380985734],"iteration":598,"passed_time":0.1633079333,"remaining_time":0.109326346},
{"learn":[0.7379628366],"iteration":599,"passed_time":0.16361965,"remaining_time":0.1090797667},
{"learn":[0.7378525429],"iteration":600,"passed_time":0.1639127828,"remaining_time":0.1088206328},
{"learn":[0.7376606749],"iteration":601,"passed_time":0.1641867484,"remaining_time":0.1085487141},
{"learn":[0.7372598061],"iteration":602,"passed_time":0.1644398802,"remaining_time":0.108263072},
{"learn":[0.7370363358],"iteration":603,"passed_time":0.1646813866,"remaining_time":0.1079699157},
{"learn":[0.7364220421],"iteration":604,"passed_time":0.1649092677,"remaining_time":0.1076680343},
{"learn":[0.7360298836],"iteration":605,"passed_time":0.1652254427,"remaining_time":0.1074238027},
{"learn":[0.7357145997],"iteration":606,"passed_time":0.1655138254,"remaining_time":0.10716134},
{"learn":[0.7356100057],"iteration":607,"passed_time":0.1657468733,"remaining_time":0.1068631157},
{"learn":[0.7355182154],"iteration":608,"passed_time":0.165999255,"remaining_time":0.1065775184},
{"learn":[0.735338146],"iteration":609,"passed_time":0.1662067606,"remaining_time":0.1062633387},
{"learn":[0.7350946232],"iteration":610,"passed_time":0.1664343916,"remaining_time":0.1059623213},
{"learn":[0.7347961919],"iteration":611,"passed_time":0.1667465249,"remaining_time":0.1057151171},
{"learn":[0.7341190384],"iteration":612,"passed_time":0.1670002817,"remaining_time":0.1054308467},
{"learn":[0.7339422011],"iteration":613,"passed_time":0.1673029148,"remaining_time":0.1051774024},
{"learn":[0.7335718465],"iteration":614,"passed_time":0.1675269624,"remaining_time":0.1048746025},
{"learn":[0.7332565264],"iteration":615,"passed_time":0.167801053,"remaining_time":0.1046032538},
{"learn":[0.7328350131],"iteration":616,"passed_time":0.1680291841,"remaining_time":0.1043033671},
{"learn":[0.7325091937],"iteration":617,"passed_time":0.1683148584,"remaining_time":0.1040392814},
{"learn":[0.7319417223],"iteration":618,"passed_time":0.1687695372,"remaining_time":0.1038791497},
{"learn":[0.73140258],"iteration":619,"passed_time":0.1690173354,"remaining_time":0.1035912701},
{"learn":[0.7311985234],"iteration":620,"passed_time":0.1692573418,"remaining_time":0.1032987642},
{"learn":[0.7311266849],"iteration":621,"passed_time":0.1694797227,"remaining_time":0.1029957157},
{"learn":[0.7307691518],"iteration":622,"passed_time":0.1697548134,"remaining_time":0.1027248229},
{"learn":[0.7303976963],"iteration":623,"passed_time":0.1700638633,"remaining_time":0.1024743792},
{"learn":[0.7301793438],"iteration":624,"passed_time":0.1702735772,"remaining_time":0.1021641463},
{"learn":[0.7296236253],"iteration":625,"passed_time":0.1704965415,"remaining_time":0.101862151},
{"learn":[0.729269228],"iteration":626,"passed_time":0.1707573401,"remaining_time":0.1015829152},
{"learn":[0.7290935599],"iteration":627,"passed_time":0.1710251389,"remaining_time":0.1013078848},
{"learn":[0.7286611115],"iteration":628,"passed_time":0.1712755206,"remaining_time":0.1010226043},
{"learn":[0.7281102559],"iteration":629,"passed_time":0.171642822,"remaining_time":0.1008061018},
{"learn":[0.728013922],"iteration":630,"passed_time":0.1718721615,"remaining_time":0.1005084431},
{"learn":[0.7276421094],"iteration":631,"passed_time":0.1721225015,"remaining_time":0.1002232287},
{"learn":[0.7272269744],"iteration":632,"passed_time":0.1723401739,"remaining_time":0.09991918457},
{"learn":[0.7270829166],"iteration":633,"passed_time":0.172593764,"remaining_time":0.09963614768},
{"learn":[0.7266713021],"iteration":634,"passed_time":0.1728322704,"remaining_time":0.09934453336},
{"learn":[0.7261813534],"iteration":635,"passed_time":0.1730908189,"remaining_time":0.09906455674},
{"learn":[0.7259365612],"iteration":636,"passed_time":0.1733365755,"remaining_time":0.09877735776},
{"learn":[0.7253521203],"iteration":637,"passed_time":0.1735913739,"remaining_time":0.09849541906},
{"learn":[0.7252300704],"iteration":638,"passed_time":0.1738036296,"remaining_time":0.09818953095},
{"learn":[0.725080604],"iteration":639,"passed_time":0.1740033016,"remaining_time":0.09787685713},
{"learn":[0.724924227],"iteration":640,"passed_time":0.1742172239,"remaining_time":0.09757251699},
{"learn":[0.7244073215],"iteration":641,"passed_time":0.174459397,"remaining_time":0.09728421206},
{"learn":[0.7240146446],"iteration":642,"passed_time":0.1747393628,"remaining_time":0.09701703349},
{"learn":[0.7236656177],"iteration":643,"passed_time":0.1750118701,"remaining_time":0.09674569216},
{"learn":[0.7233102967],"iteration":644,"passed_time":0.1752482097,"remaining_time":0.09645444101},
{"learn":[0.7231928522],"iteration":645,"passed_time":0.1755178002,"remaining_time":0.09618158094},
{"learn":[0.7228522688],"iteration":646,"passed_time":0.175721139,"remaining_time":0.09587258433},
{"learn":[0.7222872624],"iteration":647,"passed_time":0.1759538535,"remaining_time":0.09557987105},
{"learn":[0.7220192457],"iteration":648,"passed_time":0.1761736094,"remaining_time":0.09528033419},
{"learn":[0.7217828619],"iteration":649,"passed_time":0.1763928652,"remaining_time":0.09498077358},
{"learn":[0.7213983827],"iteration":650,"passed_time":0.1766475803,"remaining_time":0.09470046933},
{"learn":[0.7209290993],"iteration":651,"passed_time":0.176923546,"remaining_time":0.09443158591},
{"learn":[0.7205974032],"iteration":652,"passed_time":0.177159719,"remaining_time":0.0941415352},
{"learn":[0.7204893849],"iteration":653,"passed_time":0.177409184,"remaining_time":0.09385868142},
{"learn":[0.7201642122],"iteration":654,"passed_time":0.1776599406,"remaining_time":0.09357660995},
{"learn":[0.7197025888],"iteration":655,"passed_time":0.1780199919,"remaining_time":0.09335194697},
{"learn":[0.7193678228],"iteration":656,"passed_time":0.1783852516,"remaining_time":0.09312959103},
{"learn":[0.7190870012],"iteration":657,"passed_time":0.1786104243,"remaining_time":0.09283398952},
{"learn":[0.7186671013],"iteration":658,"passed_time":0.1788666811,"remaining_time":0.09255468628},
{"learn":[0.718465344],"iteration":659,"passed_time":0.1790740616,"remaining_time":0.09225027417},
{"learn":[0.7183264217],"iteration":660,"passed_time":0.1793399854,"remaining_time":0.0919761801},
{"learn":[0.7182236293],"iteration":661,"passed_time":0.179564408,"remaining_time":0.09168092132},
{"learn":[0.7175933732],"iteration":662,"passed_time":0.1799690438,"remaining_time":0.09147747777},
{"learn":[0.7173116501],"iteration":663,"passed_time":0.1802968025,"remaining_time":0.09123452658},
{"learn":[0.7169191202],"iteration":664,"passed_time":0.1805806018,"remaining_time":0.09096917532},
{"learn":[0.7168004157],"iteration":665,"passed_time":0.1808186914,"remaining_time":0.09068084526},
{"learn":[0.7165941849],"iteration":666,"passed_time":0.1810480309,"remaining_time":0.09038829728},
{"learn":[0.7163516945],"iteration":667,"passed_time":0.1813824981,"remaining_time":0.09014818769},
{"learn":[0.7157838356],"iteration":668,"passed_time":0.1816004206,"remaining_time":0.08985013336},
{"learn":[0.7153581782],"iteration":669,"passed_time":0.1818194264,"remaining_time":0.08955285182},
{"learn":[0.7150497919],"iteration":670,"passed_time":0.1820848085,"remaining_time":0.08927854247},
{"learn":[0.7143544511],"iteration":671,"passed_time":0.1822964808,"remaining_time":0.0889780442},
{"learn":[0.714275545],"iteration":672,"passed_time":0.182517695,"remaining_time":0.08868244617},
{"learn":[0.7135596333],"iteration":673,"passed_time":0.1827171587,"remaining_time":0.08837654856},
{"learn":[0.7133546982],"iteration":674,"passed_time":0.1829123305,"remaining_time":0.08806889989},
{"learn":[0.7129668593],"iteration":675,"passed_time":0.1832400476,"remaining_time":0.08782511157},
{"learn":[0.7123642778],"iteration":676,"passed_time":0.1835356805,"remaining_time":0.08756576779},
{"learn":[0.7120109742],"iteration":677,"passed_time":0.1838628142,"remaining_time":0.08732127754},
{"learn":[0.7119440837],"iteration":678,"passed_time":0.1841171543,"remaining_time":0.08704213038},
{"learn":[0.7115069159],"iteration":679,"passed_time":0.1843759945,"remaining_time":0.08676517389},
{"learn":[0.7111350312],"iteration":680,"passed_time":0.1846741275,"remaining_time":0.08650667645},
{"learn":[0.7108358799],"iteration":681,"passed_time":0.1849609684,"remaining_time":0.0862427976},
{"learn":[0.7107070531],"iteration":682,"passed_time":0.1852013498,"remaining_time":0.08595728829},
{"learn":[0.7104545032],"iteration":683,"passed_time":0.1854216474,"remaining_time":0.08566263241},
{"learn":[0.7104018488],"iteration":684,"passed_time":0.1857199053,"remaining_time":0.08540404405},
{"learn":[0.7100700884],"iteration":685,"passed_time":0.1859875791,"remaining_time":0.08513134088},
{"learn":[0.7095413269],"iteration":686,"passed_time":0.186222627,"remaining_time":0.08484378787},
{"learn":[0.7089912774],"iteration":687,"passed_time":0.1864603834,"remaining_time":0.08455761572},
{"learn":[0.7089510526],"iteration":688,"passed_time":0.1866629721,"remaining_time":0.0842557102},
{"learn":[0.708461855],"iteration":689,"passed_time":0.1869576883,"remaining_time":0.08399548315},
{"learn":[0.7079550469],"iteration":690,"passed_time":0.187348157,"remaining_time":0.08377797471},
{"learn":[0.7076962138],"iteration":691,"passed_time":0.1875623294,"remaining_time":0.08348149921},
{"learn":[0.7075070549],"iteration":692,"passed_time":0.1878158778,"remaining_time":0.08320270489},
{"learn":[0.7072049182],"iteration":693,"passed_time":0.1880774681,"remaining_time":0.08292752917},
{"learn":[0.7068683371],"iteration":694,"passed_time":0.1883676008,"remaining_time":0.08266491836},
{"learn":[0.7065700176],"iteration":695,"passed_time":0.1885715229,"remaining_time":0.08236457324},
{"learn":[0.7064082518],"iteration":696,"passed_time":0.1888415301,"remaining_time":0.08209323333},
{"learn":[0.7060996525],"iteration":697,"passed_time":0.1891260794,"remaining_time":0.08182818908},
{"learn":[0.7059435845],"iteration":698,"passed_time":0.1893757527,"remaining_time":0.08154807091},
{"learn":[0.705396629],"iteration":699,"passed_time":0.1896184258,"remaining_time":0.08126503964},
{"learn":[0.7047859598],"iteration":700,"passed_time":0.1899096836,"remaining_time":0.0810028465},
{"learn":[0.7047112868],"iteration":701,"passed_time":0.1901568152,"remaining_time":0.08072183892},
{"learn":[0.7046138265],"iteration":702,"passed_time":0.1904125303,"remaining_time":0.08044455406},
{"learn":[0.7043258508],"iteration":703,"passed_time":0.1906574118,"remaining_time":0.08016277543},
{"learn":[0.7038457239],"iteration":704,"passed_time":0.1908532921,"remaining_time":0.07986059739},
{"learn":[0.7036222149],"iteration":705,"passed_time":0.191062131,"remaining_time":0.07956411686},
{"learn":[0.7031067892],"iteration":706,"passed_time":0.1912610529,"remaining_time":0.07926377441},
{"learn":[0.7029577053],"iteration":707,"passed_time":0.1914598082,"remaining_time":0.07896364972},
{"learn":[0.7028668637],"iteration":708,"passed_time":0.1916463965,"remaining_time":0.07865881719},
{"learn":[0.7028404384],"iteration":709,"passed_time":0.1918925281,"remaining_time":0.07837863823},
{"learn":[0.7024849809],"iteration":710,"passed_time":0.1921204091,"remaining_time":0.07809113677},
{"learn":[0.7020903759],"iteration":711,"passed_time":0.1924316258,"remaining_time":0.07783751155},
{"learn":[0.7015996638],"iteration":712,"passed_time":0.1926522566,"remaining_time":0.07754726179},
{"learn":[0.7011593074],"iteration":713,"passed_time":0.1928632206,"remaining_time":0.07725333486},
{"learn":[0.7008175525],"iteration":714,"passed_time":0.1931370196,"remaining_time":0.07698468612},
{"learn":[0.7004509575],"iteration":715,"passed_time":0.1934520279,"remaining_time":0.07673236863},
{"learn":[0.7001046654],"iteration":716,"passed_time":0.193717785,"remaining_time":0.07646043677},
{"learn":[0.7000855454],"iteration":717,"passed_time":0.1939733752,"remaining_time":0.07618452897},
{"learn":[0.6997077173],"iteration":718,"passed_time":0.1942820501,"remaining_time":0.07592942429},
{"learn":[0.6994751404],"iteration":719,"passed_time":0.1946143506,"remaining_time":0.07568335856},
{"learn":[0.699015936],"iteration":720,"passed_time":0.1949639016,"remaining_time":0.0754437289},
{"learn":[0.698871661],"iteration":721,"passed_time":0.1952932853,"remaining_time":0.07519602953},
{"learn":[0.6984205097],"iteration":722,"passed_time":0.1956335444,"remaining_time":0.07495227081},
{"learn":[0.6983485827],"iteration":723,"passed_time":0.195930594,"remaining_time":0.07469177339},
{"learn":[0.6982465109],"iteration":724,"passed_time":0.1961424329,"remaining_time":0.07439885388},
{"learn":[0.6980182387],"iteration":725,"passed_time":0.1964193987,"remaining_time":0.07413073723},
{"learn":[0.6976285722],"iteration":726,"passed_time":0.1967440323,"remaining_time":0.07388049631},
{"learn":[0.6975216036],"iteration":727,"passed_time":0.1970984584,"remaining_time":0.07364118226},
{"learn":[0.6969562732],"iteration":728,"passed_time":0.1973941746,"remaining_time":0.07337972747},
{"learn":[0.6969478638],"iteration":729,"passed_time":0.1976787239,"remaining_time":0.07311404855},
{"learn":[0.6969088993],"iteration":730,"passed_time":0.1979223554,"remaining_time":0.07283326073},
{"learn":[0.6966430298],"iteration":731,"passed_time":0.1982379054,"remaining_time":0.07257890527},
{"learn":[0.6966173619],"iteration":732,"passed_time":0.1985227464,"remaining_time":0.07231319683},
{"learn":[0.6961094627],"iteration":733,"passed_time":0.198748044,"remaining_time":0.07202585791},
{"learn":[0.6957743407],"iteration":734,"passed_time":0.198946466,"remaining_time":0.07172899793},
{"learn":[0.695609446],"iteration":735,"passed_time":0.1992931419,"remaining_time":0.0714855835},
{"learn":[0.6954436573],"iteration":736,"passed_time":0.1995080643,"remaining_time":0.07119487232},
{"learn":[0.6952832888],"iteration":737,"passed_time":0.1997093196,"remaining_time":0.07089951455},
{"learn":[0.6951695684],"iteration":738,"passed_time":0.1999520344,"remaining_time":0.07061905411},
{"learn":[0.6947984556],"iteration":739,"passed_time":0.2001672485,"remaining_time":0.07032903325},
{"learn":[0.6946927808],"iteration":740,"passed_time":0.2004881737,"remaining_time":0.07007616328},
{"learn":[0.6945080603],"iteration":741,"passed_time":0.2007838482,"remaining_time":0.06981432998},
{"learn":[0.6939738522],"iteration":742,"passed_time":0.2010062708,"remaining_time":0.06952706811},
{"learn":[0.6937958965],"iteration":743,"passed_time":0.2012336936,"remaining_time":0.06924170101},
{"learn":[0.6936235345],"iteration":744,"passed_time":0.2015159094,"remaining_time":0.06897524416},
{"learn":[0.6933276704],"iteration":745,"passed_time":0.2019027947,"remaining_time":0.06874438319},
{"learn":[0.6931851849],"iteration":746,"passed_time":0.2022015527,"remaining_time":0.0684832568},
{"learn":[0.6927260662],"iteration":747,"passed_time":0.2025199778,"remaining_time":0.06822865563},
{"learn":[0.6922941671],"iteration":748,"passed_time":0.202763901,"remaining_time":0.06794891742},
{"learn":[0.6921434388],"iteration":749,"passed_time":0.2030817428,"remaining_time":0.06769391426},
{"learn":[0.692036204],"iteration":750,"passed_time":0.2033866259,"remaining_time":0.06743444721},
{"learn":[0.6917576879],"iteration":751,"passed_time":0.2035966732,"remaining_time":0.06714358371},
{"learn":[0.6916346912],"iteration":752,"passed_time":0.2037990536,"remaining_time":0.06685041996},
{"learn":[0.6912140939],"iteration":753,"passed_time":0.2041089785,"remaining_time":0.06659258449},
{"learn":[0.6909509205],"iteration":754,"passed_time":0.2043407347,"remaining_time":0.06630924502},
{"learn":[0.6906343176],"iteration":755,"passed_time":0.2046512429,"remaining_time":0.06605145936},
{"learn":[0.6906207825],"iteration":756,"passed_time":0.2049058747,"remaining_time":0.06577559783},
{"learn":[0.6905202985],"iteration":757,"passed_time":0.2051827571,"remaining_time":0.06550689606},
{"learn":[0.6904619919],"iteration":758,"passed_time":0.2054795567,"remaining_time":0.06524449691},
{"learn":[0.6901163217],"iteration":759,"passed_time":0.2058443164,"remaining_time":0.06500346833},
{"learn":[0.6900599335],"iteration":760,"passed_time":0.2061317407,"remaining_time":0.06473782658},
{"learn":[0.6900438446],"iteration":761,"passed_time":0.2063404129,"remaining_time":0.06444753055},
{"learn":[0.6899711607],"iteration":762,"passed_time":0.2065650022,"remaining_time":0.06416239257},
{"learn":[0.6898867386],"iteration":763,"passed_time":0.206806092,"remaining_time":0.06388251009},
{"learn":[0.689277027],"iteration":764,"passed_time":0.2071711851,"remaining_time":0.06364082155},
{"learn":[0.6892345432],"iteration":765,"passed_time":0.2074611094,"remaining_time":0.06337584805},
{"learn":[0.6889771369],"iteration":766,"passed_time":0.20766899,"remaining_time":0.06308588613},
{"learn":[0.6886486327],"iteration":767,"passed_time":0.2079377055,"remaining_time":0.06281451519},
{"learn":[0.6884024378],"iteration":768,"passed_time":0.2081805869,"remaining_time":0.06253539087},
{"learn":[0.6880082457],"iteration":769,"passed_time":0.2084363438,"remaining_time":0.06226020657},
{"learn":[0.6875480043],"iteration":770,"passed_time":0.2086393492,"remaining_time":0.06196940461},
{"learn":[0.6873127347],"iteration":771,"passed_time":0.2089246901,"remaining_time":0.06170314681},
{"learn":[0.6870957835],"iteration":772,"passed_time":0.2091872388,"remaining_time":0.06143014644},
{"learn":[0.6867102067],"iteration":773,"passed_time":0.2094042445,"remaining_time":0.06114387502},
{"learn":[0.6864028266],"iteration":774,"passed_time":0.209672835,"remaining_time":0.06087275855},
{"learn":[0.6862967844],"iteration":775,"passed_time":0.2098768405,"remaining_time":0.06058300549},
{"learn":[0.6860090321],"iteration":776,"passed_time":0.2101037632,"remaining_time":0.06030005043},
{"learn":[0.6859249752],"iteration":777,"passed_time":0.210309977,"remaining_time":0.0600113302},
{"learn":[0.6852275267],"iteration":778,"passed_time":0.2105343163,"remaining_time":0.05972796393},
{"learn":[0.6848160677],"iteration":779,"passed_time":0.2107339883,"remaining_time":0.05943779157},
{"learn":[0.6846875561],"iteration":780,"passed_time":0.2109678278,"remaining_time":0.05915743188},
{"learn":[0.6842471628],"iteration":781,"passed_time":0.2112225013,"remaining_time":0.05888299908},
{"learn":[0.6840130668],"iteration":782,"passed_time":0.2114705079,"remaining_time":0.05860676911},
{"learn":[0.6839227019],"iteration":783,"passed_time":0.2117548905,"remaining_time":0.05834063309},
{"learn":[0.6837508875],"iteration":784,"passed_time":0.2120576902,"remaining_time":0.05807949477},
{"learn":[0.6836722978],"iteration":785,"passed_time":0.2122690292,"remaining_time":0.05779334891},
{"learn":[0.683356707],"iteration":786,"passed_time":0.2125669121,"remaining_time":0.05753081611},
{"learn":[0.6832591072],"iteration":787,"passed_time":0.2128715452,"remaining_time":0.05727000963},
{"learn":[0.6832093723],"iteration":788,"passed_time":0.2131119266,"remaining_time":0.0569919094},
{"learn":[0.6829494403],"iteration":789,"passed_time":0.2133082652,"remaining_time":0.05670219708},
{"learn":[0.6829292159],"iteration":790,"passed_time":0.2135626053,"remaining_time":0.05642804615},
{"learn":[0.682562221],"iteration":791,"passed_time":0.2137916114,"remaining_time":0.05614729188},
{"learn":[0.6820248558],"iteration":792,"passed_time":0.2140745356,"remaining_time":0.05588074258},
{"learn":[0.6816599169],"iteration":793,"passed_time":0.2143124169,"remaining_time":0.05560246586},
{"learn":[0.6815690604],"iteration":794,"passed_time":0.2146084248,"remaining_time":0.05533927936},
{"learn":[0.6814431498],"iteration":795,"passed_time":0.2149757263,"remaining_time":0.05509428161},
{"learn":[0.681272035],"iteration":796,"passed_time":0.2152388999,"remaining_time":0.05482245507},
{"learn":[0.6807136514],"iteration":797,"passed_time":0.2156169517,"remaining_time":0.05457972962},
{"learn":[0.6806006487],"iteration":798,"passed_time":0.2159461688,"remaining_time":0.05432438038},
{"learn":[0.6803329573],"iteration":799,"passed_time":0.2162620522,"remaining_time":0.05406551305},
{"learn":[0.6802161059],"iteration":800,"passed_time":0.216592561,"remaining_time":0.05381013688},
{"learn":[0.6801641864],"iteration":801,"passed_time":0.2168382759,"remaining_time":0.05353363918},
{"learn":[0.6799179105],"iteration":802,"passed_time":0.2171748265,"remaining_time":0.05327950289},
{"learn":[0.6798736995],"iteration":803,"passed_time":0.2174357501,"remaining_time":0.05300672516},
{"learn":[0.6796378154],"iteration":804,"passed_time":0.2176988405,"remaining_time":0.05273450173},
{"learn":[0.679507244],"iteration":805,"passed_time":0.2179321384,"remaining_time":0.05245513008},
{"learn":[0.679089949],"iteration":806,"passed_time":0.2181592694,"remaining_time":0.05217439776},
{"learn":[0.6789675233],"iteration":807,"passed_time":0.2183831087,"remaining_time":0.05189301593},
{"learn":[0.6787436716],"iteration":808,"passed_time":0.2186721164,"remaining_time":0.05162716222},
{"learn":[0.6783919335],"iteration":809,"passed_time":0.2190018335,"remaining_time":0.05137080045},
{"learn":[0.678090622],"iteration":810,"passed_time":0.2192767158,"remaining_time":0.05110147878},
{"learn":[0.6779939002],"iteration":811,"passed_time":0.2195403062,"remaining_time":0.05082952902},
{"learn":[0.67750919],"iteration":812,"passed_time":0.2198060633,"remaining_time":0.05055809819},
{"learn":[0.6770787912],"iteration":813,"passed_time":0.2200098187,"remaining_time":0.05027251385},
{"learn":[0.6767371442],"iteration":814,"passed_time":0.2202453666,"remaining_time":0.04999434703},
{"learn":[0.6765558558],"iteration":815,"passed_time":0.2205414162,"remaining_time":0.04972992718},
{"learn":[0.6760026329],"iteration":816,"passed_time":0.2207860894,"remaining_time":0.0494539221},
{"learn":[0.6755640808],"iteration":817,"passed_time":0.221135432,"remaining_time":0.04920128194},
{"learn":[0.6753589505],"iteration":818,"passed_time":0.2214556489,"remaining_time":0.0489419688},
{"learn":[0.6752572202],"iteration":819,"passed_time":0.2217336563,"remaining_time":0.04867324162},
{"learn":[0.6751598997],"iteration":820,"passed_time":0.2219935382,"remaining_time":0.04840054},
{"learn":[0.6749185859],"iteration":821,"passed_time":0.2221997104,"remaining_time":0.04811623898},
{"learn":[0.6747888563],"iteration":822,"passed_time":0.2224255497,"remaining_time":0.04783635759},
{"learn":[0.6745044975],"iteration":823,"passed_time":0.2226814315,"remaining_time":0.04756302421},
{"learn":[0.6744056806],"iteration":824,"passed_time":0.2229086876,"remaining_time":0.047283661},
{"learn":[0.674340576],"iteration":825,"passed_time":0.2231253184,"remaining_time":0.04700218571},
{"learn":[0.6741829642],"iteration":826,"passed_time":0.2234149927,"remaining_time":0.04673614721},
{"learn":[0.6738893959],"iteration":827,"passed_time":0.223713834,"remaining_time":0.04647195586},
{"learn":[0.673375608],"iteration":828,"passed_time":0.2240164671,"remaining_time":0.04620846305},
{"learn":[0.6730252759],"iteration":829,"passed_time":0.2243612679,"remaining_time":0.04595351271},
{"learn":[0.6726809895],"iteration":830,"passed_time":0.2246022327,"remaining_time":0.04567722903},
{"learn":[0.6726671612],"iteration":831,"passed_time":0.2248016547,"remaining_time":0.04539264181},
{"learn":[0.6723219674],"iteration":832,"passed_time":0.2250674951,"remaining_time":0.04512157464},
{"learn":[0.6721371157],"iteration":833,"passed_time":0.2253981289,"remaining_time":0.04486341654},
{"learn":[0.6721262047],"iteration":834,"passed_time":0.2258984756,"remaining_time":0.04463862092},
{"learn":[0.671843324],"iteration":835,"passed_time":0.2261216482,"remaining_time":0.04435879222},
{"learn":[0.6715586635],"iteration":836,"passed_time":0.2263579461,"remaining_time":0.04408165498},
{"learn":[0.6715474351],"iteration":837,"passed_time":0.226553868,"remaining_time":0.04379680981},
{"learn":[0.6714886527],"iteration":838,"passed_time":0.2268522926,"remaining_time":0.04353184638},
{"learn":[0.6712185041],"iteration":839,"passed_time":0.2271995935,"remaining_time":0.04327611306},
{"learn":[0.6706619133],"iteration":840,"passed_time":0.227402599,"remaining_time":0.04299288137},
{"learn":[0.6704777877],"iteration":841,"passed_time":0.2276276049,"remaining_time":0.04271396862},
{"learn":[0.6701745688],"iteration":842,"passed_time":0.2279766976,"remaining_time":0.04245829362},
{"learn":[0.6700047869],"iteration":843,"passed_time":0.2281671193,"remaining_time":0.04217306945},
{"learn":[0.6698911074],"iteration":844,"passed_time":0.2283634579,"remaining_time":0.041889155},
{"learn":[0.6693693602],"iteration":845,"passed_time":0.2285652133,"remaining_time":0.04160643362},
{"learn":[0.6691426192],"iteration":846,"passed_time":0.228794636,"remaining_time":0.0413289012},
{"learn":[0.6688993678],"iteration":847,"passed_time":0.2290016415,"remaining_time":0.04104746405},
{"learn":[0.6688316265],"iteration":848,"passed_time":0.2291941883,"remaining_time":0.04076363067},
{"learn":[0.6682311542],"iteration":849,"passed_time":0.2295161969,"remaining_time":0.04050285828},
{"learn":[0.6679713603],"iteration":850,"passed_time":0.2297679536,"remaining_time":0.0402296417},
{"learn":[0.6677674439],"iteration":851,"passed_time":0.2300912122,"remaining_time":0.03996889602},
{"learn":[0.6675960179],"iteration":852,"passed_time":0.230333302,"remaining_time":0.03969401571},
{"learn":[0.6673524408],"iteration":853,"passed_time":0.2305767252,"remaining_time":0.03941944013},
{"learn":[0.6670425307],"iteration":854,"passed_time":0.230806773,"remaining_time":0.0391426691},
{"learn":[0.6666056936],"iteration":855,"passed_time":0.2310374041,"remaining_time":0.03886610536},
{"learn":[0.666380775],"iteration":856,"passed_time":0.231247743,"remaining_time":0.03858626284},
{"learn":[0.6660178292],"iteration":857,"passed_time":0.2314395398,"remaining_time":0.03830351358},
{"learn":[0.6657646924],"iteration":858,"passed_time":0.2316552539,"remaining_time":0.03802490198},
{"learn":[0.66549038],"iteration":859,"passed_time":0.2318870517,"remaining_time":0.03774905493},
{"learn":[0.6652795466],"iteration":860,"passed_time":0.2321382668,"remaining_time":0.03747644492},
{"learn":[0.6650861914],"iteration":861,"passed_time":0.2324153575,"remaining_time":0.03720802707},
{"learn":[0.6649466627],"iteration":862,"passed_time":0.2326750727,"remaining_time":0.03693683078},
{"learn":[0.6646301783],"iteration":863,"passed_time":0.233048041,"remaining_time":0.03668348793},
{"learn":[0.6644902986],"iteration":864,"passed_time":0.2333480907,"remaining_time":0.03641848814},
{"learn":[0.6642346203],"iteration":865,"passed_time":0.2337826022,"remaining_time":0.03617421328},
{"learn":[0.663978937],"iteration":866,"passed_time":0.2339950662,"remaining_time":0.03589543692},
{"learn":[0.6637797013],"iteration":867,"passed_time":0.2342040718,"remaining_time":0.03561628741},
{"learn":[0.6634004977],"iteration":868,"passed_time":0.2344898294,"remaining_time":0.03534886956},
{"learn":[0.6633502799],"iteration":869,"passed_time":0.234789129,"remaining_time":0.03508343307},
{"learn":[0.6631872641],"iteration":870,"passed_time":0.2350100099,"remaining_time":0.03480630457},
{"learn":[0.6630983787],"iteration":871,"passed_time":0.2352217656,"remaining_time":0.03452796559},
{"learn":[0.6630949554],"iteration":872,"passed_time":0.235427396,"remaining_time":0.03424888808},
{"learn":[0.662951606],"iteration":873,"passed_time":0.2356911531,"remaining_time":0.03397835845},
{"learn":[0.6626664616],"iteration":874,"passed_time":0.235912784,"remaining_time":0.03370182628},
{"learn":[0.6626624569],"iteration":875,"passed_time":0.2361302064,"remaining_time":0.03342482374},
{"learn":[0.6624708663],"iteration":876,"passed_time":0.2363836715,"remaining_time":0.03315301208},
{"learn":[0.6623814805],"iteration":877,"passed_time":0.2366855962,"remaining_time":0.03288797578},
{"learn":[0.6621064334],"iteration":878,"passed_time":0.2369602285,"remaining_time":0.03261909858},
{"learn":[0.6620143458],"iteration":879,"passed_time":0.2372064018,"remaining_time":0.03234632751},
{"learn":[0.6617972458],"iteration":880,"passed_time":0.2374234492,"remaining_time":0.0320696827},
{"learn":[0.6617435259],"iteration":881,"passed_time":0.2376747476,"remaining_time":0.03179775534},
{"learn":[0.6615622998],"iteration":882,"passed_time":0.2378865865,"remaining_time":0.03152064624},
{"learn":[0.6609754021],"iteration":883,"passed_time":0.2382643049,"remaining_time":0.03126545178},
{"learn":[0.6609417996],"iteration":884,"passed_time":0.2385549377,"remaining_time":0.03099866422},
{"learn":[0.6607332913],"iteration":885,"passed_time":0.2387561514,"remaining_time":0.03072031745},
{"learn":[0.660340018],"iteration":886,"passed_time":0.2390464924,"remaining_time":0.03045349904},
{"learn":[0.65994468],"iteration":887,"passed_time":0.2392879572,"remaining_time":0.03018046307},
{"learn":[0.6597266565],"iteration":888,"passed_time":0.2396094241,"remaining_time":0.02991748715},
{"learn":[0.6596541676],"iteration":889,"passed_time":0.2398924316,"remaining_time":0.02964962638},
{"learn":[0.6592580499],"iteration":890,"passed_time":0.2402553163,"remaining_time":0.02939150334},
{"learn":[0.659204762],"iteration":891,"passed_time":0.240543074,"remaining_time":0.02912404932},
{"learn":[0.658949015],"iteration":892,"passed_time":0.2408153312,"remaining_time":0.02885469254},
{"learn":[0.6588731504],"iteration":893,"passed_time":0.24108313,"remaining_time":0.02858480065},
{"learn":[0.6586974434],"iteration":894,"passed_time":0.2413217614,"remaining_time":0.02831149156},
{"learn":[0.6584704286],"iteration":895,"passed_time":0.2416058106,"remaining_time":0.02804353159},
{"learn":[0.6583951113],"iteration":896,"passed_time":0.2418808596,"remaining_time":0.02777450227},
{"learn":[0.6583803226],"iteration":897,"passed_time":0.2421551169,"remaining_time":0.02750536963},
{"learn":[0.6580418741],"iteration":898,"passed_time":0.2424138738,"remaining_time":0.02723448415},
{"learn":[0.6578107441],"iteration":899,"passed_time":0.2426652555,"remaining_time":0.02696280617},
{"learn":[0.6577163125],"iteration":900,"passed_time":0.2429895975,"remaining_time":0.02669918996},
{"learn":[0.6573769038],"iteration":901,"passed_time":0.2431907695,"remaining_time":0.026422057},
{"learn":[0.6570943693],"iteration":902,"passed_time":0.243434526,"remaining_time":0.02614966669},
{"learn":[0.6568236581],"iteration":903,"passed_time":0.2436908245,"remaining_time":0.02587867163},
{"learn":[0.6567896386],"iteration":904,"passed_time":0.2439784571,"remaining_time":0.02561099826},
{"learn":[0.6566680275],"iteration":905,"passed_time":0.2442737983,"remaining_time":0.02534408062},
{"learn":[0.6566631662],"iteration":906,"passed_time":0.2444871374,"remaining_time":0.02506869214},
{"learn":[0.6565963554],"iteration":907,"passed_time":0.244697893,"remaining_time":0.02479317858},
{"learn":[0.6565854954],"iteration":908,"passed_time":0.2449485247,"remaining_time":0.0245217995},
{"learn":[0.6563542011],"iteration":909,"passed_time":0.2451982813,"remaining_time":0.02425037947},
{"learn":[0.656349839],"iteration":910,"passed_time":0.2454513714,"remaining_time":0.02397933266},
{"learn":[0.6561780627],"iteration":911,"passed_time":0.245750921,"remaining_time":0.02371280817},
{"learn":[0.6558745018],"iteration":912,"passed_time":0.2461118473,"remaining_time":0.02345205993},
{"learn":[0.6556523811],"iteration":913,"passed_time":0.2464237723,"remaining_time":0.02318648186},
{"learn":[0.6556068552],"iteration":914,"passed_time":0.2467006963,"remaining_time":0.02291755102},
{"learn":[0.655234599],"iteration":915,"passed_time":0.24696487,"remaining_time":0.0226474335},
{"learn":[0.6551393659],"iteration":916,"passed_time":0.2471700005,"remaining_time":0.02237198478},
{"learn":[0.6547354865],"iteration":917,"passed_time":0.2474314658,"remaining_time":0.02210172135},
{"learn":[0.6547319418],"iteration":918,"passed_time":0.2476219709,"remaining_time":0.02182522268},
{"learn":[0.6545091394],"iteration":919,"passed_time":0.2478835612,"remaining_time":0.02155509228},
{"learn":[0.6542841657],"iteration":920,"passed_time":0.2481300261,"remaining_time":0.02128368302},
{"learn":[0.6542057166],"iteration":921,"passed_time":0.2483785327,"remaining_time":0.0210125006},
{"learn":[0.6539029685],"iteration":922,"passed_time":0.2486107889,"remaining_time":0.02074001164},
{"learn":[0.6537118005],"iteration":923,"passed_time":0.2488348782,"remaining_time":0.02046693803},
{"learn":[0.6535224365],"iteration":924,"passed_time":0.2491749706,"remaining_time":0.02020337599},
{"learn":[0.6533088648],"iteration":925,"passed_time":0.2494659783,"remaining_time":0.01993572613},
{"learn":[0.6532287045],"iteration":926,"passed_time":0.2497501109,"remaining_time":0.01966748446},
{"learn":[0.6531925694],"iteration":927,"passed_time":0.2500378269,"remaining_time":0.01939948657},
{"learn":[0.6531798347],"iteration":928,"passed_time":0.2503033756,"remaining_time":0.01912975207},
{"learn":[0.6528079025],"iteration":929,"passed_time":0.250556799,"remaining_time":0.01885911391},
{"learn":[0.6524839966],"iteration":930,"passed_time":0.2508390982,"remaining_time":0.01859065282},
{"learn":[0.6522141263],"iteration":931,"passed_time":0.2510634375,"remaining_time":0.01831793321},
{"learn":[0.6517883899],"iteration":932,"passed_time":0.2512878602,"remaining_time":0.01804532329},
{"learn":[0.6516495662],"iteration":933,"passed_time":0.2516109938,"remaining_time":0.01777979185},
{"learn":[0.651143858],"iteration":934,"passed_time":0.2519768785,"remaining_time":0.0175171092},
{"learn":[0.65107435],"iteration":935,"passed_time":0.2523648472,"remaining_time":0.01725571605},
{"learn":[0.6508478467],"iteration":936,"passed_time":0.2526971477,"remaining_time":0.01699030983},
{"learn":[0.6508394127],"iteration":937,"passed_time":0.2529259038,"remaining_time":0.01671791688},
{"learn":[0.6501985498],"iteration":938,"passed_time":0.2531991611,"remaining_time":0.0164485078},
{"learn":[0.6498660088],"iteration":939,"passed_time":0.2533971247,"remaining_time":0.01617428456},
{"learn":[0.6494718553],"iteration":940,"passed_time":0.2536307143,"remaining_time":0.01590245711},
{"learn":[0.649440125],"iteration":941,"passed_time":0.2539981824,"remaining_time":0.0156389539},
{"learn":[0.6491528354],"iteration":942,"passed_time":0.254310024,"remaining_time":0.01537186784},
{"learn":[0.6490683251],"iteration":943,"passed_time":0.254608407,"remaining_time":0.01510388855},
{"learn":[0.6487463327],"iteration":944,"passed_time":0.2548376631,"remaining_time":0.01483182166},
{"learn":[0.6486557736],"iteration":945,"passed_time":0.2551321292,"remaining_time":0.01456356763},
{"learn":[0.648651596],"iteration":946,"passed_time":0.2554453043,"remaining_time":0.01429630531},
{"learn":[0.6483172485],"iteration":947,"passed_time":0.2556475596,"remaining_time":0.01402286192},
{"learn":[0.6480797433],"iteration":948,"passed_time":0.2558856493,"remaining_time":0.01375149433},
{"learn":[0.6478943109],"iteration":949,"passed_time":0.2560874464,"remaining_time":0.01347828665},
{"learn":[0.647673543],"iteration":950,"passed_time":0.2563557035,"remaining_time":0.01320865349},
{"learn":[0.6474950458],"iteration":951,"passed_time":0.256561959,"remaining_time":0.01293589709},
{"learn":[0.6473222784],"iteration":952,"passed_time":0.2568443832,"remaining_time":0.01266703674},
{"learn":[0.6469335974],"iteration":953,"passed_time":0.2571054318,"remaining_time":0.01239711726},
{"learn":[0.6466818507],"iteration":954,"passed_time":0.2573996896,"remaining_time":0.01212878119},
{"learn":[0.6465573793],"iteration":955,"passed_time":0.2576239456,"remaining_time":0.01185716905},
{"learn":[0.646508688],"iteration":956,"passed_time":0.2578882027,"remaining_time":0.0115874532},
{"learn":[0.646412975],"iteration":957,"passed_time":0.2581491679,"remaining_time":0.01131760444},
{"learn":[0.6463145728],"iteration":958,"passed_time":0.258415675,"remaining_time":0.01104801113},
{"learn":[0.6460667316],"iteration":959,"passed_time":0.2587989769,"remaining_time":0.0107832907},
{"learn":[0.6457538547],"iteration":960,"passed_time":0.2591046101,"remaining_time":0.01051517148},
{"learn":[0.6455945483],"iteration":961,"passed_time":0.2593954511,"remaining_time":0.01024638996},
{"learn":[0.6454528173],"iteration":962,"passed_time":0.2596651667,"remaining_time":0.009976750952},
{"learn":[0.6452432784],"iteration":963,"passed_time":0.2599228402,"remaining_time":0.009706662082},
{"learn":[0.6451465396],"iteration":964,"passed_time":0.2601935141,"remaining_time":0.009437070458},
{"learn":[0.6450886068],"iteration":965,"passed_time":0.2604292287,"remaining_time":0.009166246144},
{"learn":[0.6448285677],"iteration":966,"passed_time":0.2607307784,"remaining_time":0.008897741144},
{"learn":[0.644694711],"iteration":967,"passed_time":0.2611077051,"remaining_time":0.008631659672},
{"learn":[0.6446713941],"iteration":968,"passed_time":0.261380629,"remaining_time":0.008362022187},
{"learn":[0.644594779],"iteration":969,"passed_time":0.2617640976,"remaining_time":0.008095796832},
{"learn":[0.6442851807],"iteration":970,"passed_time":0.2620160626,"remaining_time":0.007825402488},
{"learn":[0.6440988901],"iteration":971,"passed_time":0.2622751945,"remaining_time":0.007555252517},
{"learn":[0.6438492658],"iteration":972,"passed_time":0.2625582854,"remaining_time":0.007285790036},
{"learn":[0.6434355019],"iteration":973,"passed_time":0.2628035419,"remaining_time":0.00701528962},
{"learn":[0.6430815394],"iteration":974,"passed_time":0.2630705074,"remaining_time":0.006745397625},
{"learn":[0.6426474921],"iteration":975,"passed_time":0.2633625151,"remaining_time":0.006476127422},
{"learn":[0.6424190772],"iteration":976,"passed_time":0.2636528145,"remaining_time":0.006206770455},
{"learn":[0.6421020049],"iteration":977,"passed_time":0.2638769038,"remaining_time":0.005935881273},
{"learn":[0.6420927945],"iteration":978,"passed_time":0.2642095794,"remaining_time":0.005667416922},
{"learn":[0.6420844121],"iteration":979,"passed_time":0.2644937536,"remaining_time":0.005397831706},
{"learn":[0.6419126888],"iteration":980,"passed_time":0.2647577606,"remaining_time":0.005127826149},
{"learn":[0.641529117],"iteration":981,"passed_time":0.2649737664,"remaining_time":0.004856952948},
{"learn":[0.641432631],"iteration":982,"passed_time":0.265184397,"remaining_time":0.004586098422},
{"learn":[0.6412330899],"iteration":983,"passed_time":0.2653939859,"remaining_time":0.004315349365},
{"learn":[0.6410426036],"iteration":984,"passed_time":0.2656024915,"remaining_time":0.004044707992},
{"learn":[0.6407152492],"iteration":985,"passed_time":0.2658506231,"remaining_time":0.003774755297},
{"learn":[0.640639342],"iteration":986,"passed_time":0.2660694206,"remaining_time":0.003504460453},
{"learn":[0.6404286102],"iteration":987,"passed_time":0.2663079269,"remaining_time":0.003234509234},
{"learn":[0.6402476093],"iteration":988,"passed_time":0.2665095573,"remaining_time":0.002964211456},
{"learn":[0.6400847076],"iteration":989,"passed_time":0.2667920648,"remaining_time":0.002694869342},
{"learn":[0.6399418567],"iteration":990,"passed_time":0.2670421965,"remaining_time":0.002425206628},
{"learn":[0.6394348054],"iteration":991,"passed_time":0.2673487047,"remaining_time":0.002156037941},
{"learn":[0.6393532322],"iteration":992,"passed_time":0.2676472543,"remaining_time":0.001886737946},
{"learn":[0.6391538303],"iteration":993,"passed_time":0.26792297,"remaining_time":0.001617241267},
{"learn":[0.6391245553],"iteration":994,"passed_time":0.2681154751,"remaining_time":0.001347313945},
{"learn":[0.638956379],"iteration":995,"passed_time":0.2683667318,"remaining_time":0.001077778039},
{"learn":[0.6387613549],"iteration":996,"passed_time":0.2686189885,"remaining_time":0.0008082818109},
{"learn":[0.6384855907],"iteration":997,"passed_time":0.2689274134,"remaining_time":0.0005389326921},
{"learn":[0.6381652502],"iteration":998,"passed_time":0.269212921,"remaining_time":0.0002694824034},
{"learn":[0.6379441718],"iteration":999,"passed_time":0.2694873866,"remaining_time":0}
]}